<archimate:ArchimateDiagramModel
    xmlns:xsi="http://www.w3.org/2001/XMLSchema-instance"
    xmlns:archimate="http://www.archimatetool.com/archimate"
    name="GP03 Dienstverlening naar klanten view"
    id="id-e31983fd-2ca7-4134-9fda-0a11457c7167">
  <children
      xsi:type="archimate:DiagramModelNote"
      id="id-62406"
      font="1|arial|16.0|0|WINDOWS|1|-15|0|0|0|0|0|0|0|0|3|2|1|34|arial"
      fontColor="#000000"
      lineColor="#808080"
      textAlignment="1"
      fillColor="#e1e1e1"
      content="Besloten kanaal voor klanten">
    <bounds
        x="100"
        y="440"
        width="447"
        height="493"/>
  </children>
  <children
      xsi:type="archimate:DiagramModelArchimateObject"
      id="id-61087"
      targetConnections="id-61135"
      font="1|Segoe UI|10.0|0|WINDOWS|1|-15|0|0|0|0|0|0|0|0|3|2|1|34|Segoe UI"
      lineColor="#000000"
      fillColor="#daeef3"
      type="1">
    <sourceConnections
        xsi:type="archimate:DiagramModelArchimateConnection"
        id="id-61136"
        font="1|Segoe UI|10.0|0|WINDOWS|1|-15|0|0|0|0|0|0|0|0|3|2|1|34|Segoe UI"
        fontColor="#000000"
        lineColor="#000000"
        source="id-61087"
        target="id-61111">
      <archimateRelationship
          xsi:type="archimate:FlowRelationship"
          href="FlowRelationship_id-cddf1a03-99b5-4ab9-882d-7dfaaa50ee67.xml#id-cddf1a03-99b5-4ab9-882d-7dfaaa50ee67"/>
    </sourceConnections>
    <bounds
        x="153"
        y="767"
        width="336"
        height="92"/>
    <archimateElement
        xsi:type="archimate:ApplicationComponent"
        href="ApplicationComponent_id-5c9f683b-4454-4e3e-b93c-da50dfd6934a.xml#id-5c9f683b-4454-4e3e-b93c-da50dfd6934a"/>
  </children>
  <children
      xsi:type="archimate:DiagramModelArchimateObject"
      id="id-61088"
      targetConnections="id-61138 id-61139"
      font="1|Segoe UI|10.0|0|WINDOWS|1|-15|0|0|0|0|0|0|0|0|3|2|1|34|Segoe UI"
      lineColor="#000000"
      fillColor="#daeef3"
      type="1">
    <bounds
        x="153"
        y="507"
        width="336"
        height="92"/>
    <archimateElement
        xsi:type="archimate:ApplicationComponent"
        href="ApplicationComponent_id-96f66a08-8e0b-4602-944b-73ca3ba659f2.xml#id-96f66a08-8e0b-4602-944b-73ca3ba659f2"/>
  </children>
  <children
      xsi:type="archimate:DiagramModelNote"
      id="id-62408"
      font="1|arial|16.0|0|WINDOWS|1|-15|0|0|0|0|0|0|0|0|3|2|1|34|arial"
      fontColor="#000000"
      lineColor="#808080"
      textAlignment="1"
      fillColor="#e1e1e1"
      content="Publiek kanaal voor klanten">
    <bounds
        x="100"
        y="60"
        width="447"
        height="333"/>
  </children>
  <children
      xsi:type="archimate:DiagramModelArchimateObject"
      id="id-61089"
      targetConnections="id-61134"
      font="1|Segoe UI|10.0|0|WINDOWS|1|-15|0|0|0|0|0|0|0|0|3|2|1|34|Segoe UI"
      lineColor="#000000"
      fillColor="#daeef3"
      type="1">
    <bounds
        x="153"
        y="260"
        width="336"
        height="92"/>
    <archimateElement
        xsi:type="archimate:ApplicationComponent"
        href="ApplicationComponent_id-c48436af-1f4e-433c-a748-19b2bd28ac0b.xml#id-c48436af-1f4e-433c-a748-19b2bd28ac0b"/>
  </children>
  <children
      xsi:type="archimate:DiagramModelArchimateObject"
      id="id-61090"
      targetConnections="id-61131"
      font="1|Segoe UI|10.0|0|WINDOWS|1|-15|0|0|0|0|0|0|0|0|3|2|1|34|Segoe UI"
      lineColor="#000000"
      fillColor="#daeef3"
      type="1">
    <bounds
        x="153"
        y="120"
        width="336"
        height="92"/>
    <archimateElement
        xsi:type="archimate:ApplicationComponent"
        href="ApplicationComponent_id-8c8117ec-8fcf-4e2c-ab31-cda3f4570642.xml#id-8c8117ec-8fcf-4e2c-ab31-cda3f4570642"/>
  </children>
  <children
      xsi:type="archimate:DiagramModelNote"
      id="id-62410"
      font="1|arial|16.0|0|WINDOWS|1|-15|0|0|0|0|0|0|0|0|3|2|1|34|arial"
      fontColor="#000000"
      lineColor="#808080"
      textAlignment="1"
      fillColor="#e1e1e1"
      content="Gemeentelijke Informatievoorziening">
    <bounds
        x="770"
        y="60"
        width="1561"
        height="1053"/>
  </children>
  <children
      xsi:type="archimate:DiagramModelArchimateObject"
      id="id-61102"
      targetConnections="id-a018c47be08d48cda717787fac3142b3"
      font="1|Segoe UI|10.0|0|WINDOWS|1|-15|0|0|0|0|0|0|0|0|3|2|1|34|Segoe UI"
      lineColor="#000000"
      fillColor="#daeef3"
      type="1">
    <sourceConnections
        xsi:type="archimate:DiagramModelArchimateConnection"
        id="id-61105"
        font="1|Segoe UI|10.0|0|WINDOWS|1|-15|0|0|0|0|0|0|0|0|3|2|1|34|Segoe UI"
        fontColor="#000000"
        lineColor="#000000"
        source="id-61102"
        target="id-61121">
      <bendpoints
          startX="65"
          startY="-68"
          endX="65"
          endY="107"/>
      <archimateRelationship
          xsi:type="archimate:FlowRelationship"
          href="FlowRelationship_id-19f25fbd-2bdf-429a-afc4-c137543fc94a.xml#id-19f25fbd-2bdf-429a-afc4-c137543fc94a"/>
    </sourceConnections>
    <sourceConnections
        xsi:type="archimate:DiagramModelArchimateConnection"
        id="id-61103"
        font="1|Segoe UI|10.0|0|WINDOWS|1|-15|0|0|0|0|0|0|0|0|3|2|1|34|Segoe UI"
        fontColor="#000000"
        lineColor="#000000"
        source="id-61102"
        target="id-61121">
      <bendpoints
          startX="-75"
          startY="-98"
          endX="-75"
          endY="77"/>
      <archimateRelationship
          xsi:type="archimate:FlowRelationship"
          href="FlowRelationship_id-53a89b69-d104-4adc-9fef-526536afaf52.xml#id-53a89b69-d104-4adc-9fef-526536afaf52"/>
    </sourceConnections>
    <bounds
        x="1377"
        y="682"
        width="336"
        height="92"/>
    <archimateElement
        xsi:type="archimate:ApplicationComponent"
        href="ApplicationComponent_id-f2dfbd0b-9d36-405c-bdbe-827f3296de29.xml#id-f2dfbd0b-9d36-405c-bdbe-827f3296de29"/>
  </children>
  <children
      xsi:type="archimate:DiagramModelArchimateObject"
      id="id-61107"
      targetConnections="id-61122"
      font="1|Segoe UI|10.0|0|WINDOWS|1|-15|0|0|0|0|0|0|0|0|3|2|1|34|Segoe UI"
      lineColor="#000000"
      fillColor="#daeef3"
      type="1">
    <sourceConnections
        xsi:type="archimate:DiagramModelArchimateConnection"
        id="id-61097"
        font="1|Segoe UI|10.0|0|WINDOWS|1|-15|0|0|0|0|0|0|0|0|3|2|1|34|Segoe UI"
        fontColor="#000000"
        lineColor="#000000"
        source="id-61107"
        target="id-61096">
      <bendpoints
          startX="106"
          startY="-253"
          endX="1086"
          endY="-6"/>
      <archimateRelationship
          xsi:type="archimate:FlowRelationship"
          href="FlowRelationship_id-778a2b2a-3d96-4488-84d6-27f11cb4c3a6.xml#id-778a2b2a-3d96-4488-84d6-27f11cb4c3a6"/>
    </sourceConnections>
    <sourceConnections
        xsi:type="archimate:DiagramModelArchimateConnection"
        id="id-61099"
        font="1|Segoe UI|10.0|0|WINDOWS|1|-15|0|0|0|0|0|0|0|0|3|2|1|34|Segoe UI"
        fontColor="#000000"
        lineColor="#000000"
        source="id-61107"
        target="id-61121">
      <bendpoints
          startX="-95"
          startY="77"
          endX="365"
          endY="77"/>
      <bendpoints
          startX="-365"
          startY="77"
          endX="95"
          endY="77"/>
      <archimateRelationship
          xsi:type="archimate:FlowRelationship"
          href="FlowRelationship_id-2f9a17de-21bc-4af9-98fb-517f3dbf2494.xml#id-2f9a17de-21bc-4af9-98fb-517f3dbf2494"/>
    </sourceConnections>
    <sourceConnections
        xsi:type="archimate:DiagramModelArchimateConnection"
        id="id-61125"
        font="1|Segoe UI|10.0|0|WINDOWS|1|-15|0|0|0|0|0|0|0|0|3|2|1|34|Segoe UI"
        fontColor="#000000"
        lineColor="#000000"
        source="id-61107"
        target="id-61121">
      <bendpoints
          startX="-95"
          startY="-83"
          endX="365"
          endY="-83"/>
      <bendpoints
          startX="-365"
          startY="-83"
          endX="95"
          endY="-83"/>
      <archimateRelationship
          xsi:type="archimate:FlowRelationship"
          href="FlowRelationship_id-d1b242f1-2cad-47d6-85bd-1c4c44539bed.xml#id-d1b242f1-2cad-47d6-85bd-1c4c44539bed"/>
    </sourceConnections>
    <sourceConnections
        xsi:type="archimate:DiagramModelArchimateConnection"
        id="id-61109"
        font="1|Segoe UI|10.0|0|WINDOWS|1|-15|0|0|0|0|0|0|0|0|3|2|1|34|Segoe UI"
        fontColor="#000000"
        lineColor="#000000"
        source="id-61107"
        target="id-61108">
      <bendpoints
          startX="195"
          startY="-3"
          endX="1175"
          endY="-463"/>
      <bendpoints
          startX="195"
          startY="377"
          endX="1175"
          endY="-83"/>
      <bendpoints
          startX="-875"
          startY="377"
          endX="105"
          endY="-83"/>
      <archimateRelationship
          xsi:type="archimate:FlowRelationship"
          href="FlowRelationship_id-a37cb0a5-eca7-4bbe-ae58-693994b99525.xml#id-a37cb0a5-eca7-4bbe-ae58-693994b99525"/>
    </sourceConnections>
    <sourceConnections
        xsi:type="archimate:DiagramModelArchimateConnection"
        id="id-61113"
        font="1|Segoe UI|10.0|0|WINDOWS|1|-15|0|0|0|0|0|0|0|0|3|2|1|34|Segoe UI"
        fontColor="#000000"
        lineColor="#000000"
        source="id-61107"
        target="id-61112">
      <bendpoints
          startX="-5"
          startY="-123"
          endX="975"
          endY="-123"/>
      <bendpoints
          startX="-945"
          startY="-123"
          endX="35"
          endY="-123"/>
      <archimateRelationship
          xsi:type="archimate:FlowRelationship"
          href="FlowRelationship_id-040cfa70-6ef0-4fcf-88cf-a025d266f92b.xml#id-040cfa70-6ef0-4fcf-88cf-a025d266f92b"/>
    </sourceConnections>
    <bounds
        x="1837"
        y="507"
        width="336"
        height="92"/>
    <archimateElement
        xsi:type="archimate:ApplicationComponent"
        href="ApplicationComponent_id-7a855337-fcbb-11e5-11ba-005056a85f9c.xml#id-7a855337-fcbb-11e5-11ba-005056a85f9c"/>
  </children>
  <children
      xsi:type="archimate:DiagramModelArchimateObject"
      id="id-61108"
      targetConnections="id-61127 id-61117 id-61109"
      font="1|Segoe UI|10.0|0|WINDOWS|1|-15|0|0|0|0|0|0|0|0|3|2|1|34|Segoe UI"
      lineColor="#000000"
      fillColor="#daeef3"
      type="1">
    <sourceConnections
        xsi:type="archimate:DiagramModelArchimateConnection"
        id="id-61135"
        font="1|Segoe UI|10.0|0|WINDOWS|1|-15|0|0|0|0|0|0|0|0|3|2|1|34|Segoe UI"
        fontColor="#000000"
        lineColor="#000000"
        source="id-61108"
        target="id-61087">
      <bendpoints
          startX="-608"
          startY="-6"
          endX="-8"
          endY="194"/>
      <archimateRelationship
          xsi:type="archimate:FlowRelationship"
          href="FlowRelationship_id-b5fb30b0-d1b9-4143-8e09-3c8475761048.xml#id-b5fb30b0-d1b9-4143-8e09-3c8475761048"/>
    </sourceConnections>
    <bounds
        x="857"
        y="967"
        width="336"
        height="92"/>
    <archimateElement
        xsi:type="archimate:ApplicationComponent"
        href="ApplicationComponent_id-8c2cf498-380a-4fc1-b8ce-becf802d6371.xml#id-8c2cf498-380a-4fc1-b8ce-becf802d6371"/>
  </children>
  <children
      xsi:type="archimate:DiagramModelArchimateObject"
      id="id-61111"
      targetConnections="id-61136"
      font="1|Segoe UI|10.0|0|WINDOWS|1|-15|0|0|0|0|0|0|0|0|3|2|1|34|Segoe UI"
      lineColor="#000000"
      fillColor="#daeef3"
      type="1">
    <sourceConnections
        xsi:type="archimate:DiagramModelArchimateConnection"
        id="id-61122"
        font="1|Segoe UI|10.0|0|WINDOWS|1|-15|0|0|0|0|0|0|0|0|3|2|1|34|Segoe UI"
        fontColor="#000000"
        lineColor="#000000"
        source="id-61111"
        target="id-61107">
      <bendpoints
          startX="286"
          startY="1"
          endX="-694"
          endY="261"/>
      <bendpoints
          startX="979"
          startY="1"
          endX="-1"
          endY="261"/>
      <archimateRelationship
          xsi:type="archimate:FlowRelationship"
          href="FlowRelationship_id-944220fa-279a-42f2-baf0-6be5a78b0e23.xml#id-944220fa-279a-42f2-baf0-6be5a78b0e23"/>
    </sourceConnections>
    <sourceConnections
        xsi:type="archimate:DiagramModelArchimateConnection"
        id="id-a018c47be08d48cda717787fac3142b3"
        source="id-61111"
        target="id-61102">
      <bendpoints
          startX="125"
          startY="-83"
          endX="-395"
          endY="2"/>
      <archimateRelationship
          xsi:type="archimate:FlowRelationship"
          href="FlowRelationship_id-107b4507-8664-4cc6-bb9b-8e1a4214b2d0.xml#id-107b4507-8664-4cc6-bb9b-8e1a4214b2d0"/>
    </sourceConnections>
    <bounds
        x="857"
        y="767"
        width="336"
        height="92"/>
    <archimateElement
        xsi:type="archimate:ApplicationComponent"
        href="ApplicationComponent_id-8c2cf498-380a-4fc1-b8ce-becf802d6371.xml#id-8c2cf498-380a-4fc1-b8ce-becf802d6371"/>
  </children>
  <children
      xsi:type="archimate:DiagramModelArchimateObject"
      id="id-61112"
      targetConnections="id-61113 id-61119 id-61123"
      font="1|Segoe UI|10.0|0|WINDOWS|1|-15|0|0|0|0|0|0|0|0|3|2|1|34|Segoe UI"
      lineColor="#000000"
      fillColor="#daeef3"
      type="1">
    <sourceConnections
        xsi:type="archimate:DiagramModelArchimateConnection"
        id="id-61138"
        font="1|Segoe UI|10.0|0|WINDOWS|1|-15|0|0|0|0|0|0|0|0|3|2|1|34|Segoe UI"
        fontColor="#000000"
        lineColor="#000000"
        source="id-61112"
        target="id-61088">
      <bendpoints
          startX="-355"
          startY="27"
          endX="349"
          endY="27"/>
      <archimateRelationship
          xsi:type="archimate:FlowRelationship"
          href="FlowRelationship_id-85a86a5a-172a-4022-ab58-24d3072edbf1.xml#id-85a86a5a-172a-4022-ab58-24d3072edbf1"/>
    </sourceConnections>
    <sourceConnections
        xsi:type="archimate:DiagramModelArchimateConnection"
        id="id-61139"
        font="1|Segoe UI|10.0|0|WINDOWS|1|-15|0|0|0|0|0|0|0|0|3|2|1|34|Segoe UI"
        fontColor="#000000"
        lineColor="#000000"
        source="id-61112"
        target="id-61088">
      <archimateRelationship
          xsi:type="archimate:FlowRelationship"
          href="FlowRelationship_id-54548e71-8f7b-48f2-8c6a-cef64e935f95.xml#id-54548e71-8f7b-48f2-8c6a-cef64e935f95"/>
    </sourceConnections>
    <bounds
        x="857"
        y="507"
        width="336"
        height="92"/>
    <archimateElement
        xsi:type="archimate:ApplicationComponent"
        href="ApplicationComponent_id-8c2cf498-380a-4fc1-b8ce-becf802d6371.xml#id-8c2cf498-380a-4fc1-b8ce-becf802d6371"/>
  </children>
  <children
      xsi:type="archimate:DiagramModelArchimateObject"
      id="id-61115"
      targetConnections="id-61094"
      font="1|Segoe UI|10.0|0|WINDOWS|1|-15|0|0|0|0|0|0|0|0|3|2|1|34|Segoe UI"
      lineColor="#000000"
      fillColor="#daeef3"
      type="1">
    <sourceConnections
        xsi:type="archimate:DiagramModelArchimateConnection"
        id="id-61131"
        font="1|Segoe UI|10.0|0|WINDOWS|1|-15|0|0|0|0|0|0|0|0|3|2|1|34|Segoe UI"
        fontColor="#000000"
        lineColor="#000000"
        source="id-61115"
        target="id-61090">
      <archimateRelationship
          xsi:type="archimate:FlowRelationship"
          href="FlowRelationship_id-1ed48ce2-9732-4ae7-9bbc-8f7d9ee1e0e5.xml#id-1ed48ce2-9732-4ae7-9bbc-8f7d9ee1e0e5"/>
    </sourceConnections>
    <bounds
        x="857"
        y="120"
        width="336"
        height="92"/>
    <archimateElement
        xsi:type="archimate:ApplicationComponent"
        href="ApplicationComponent_id-8c8117ec-8fcf-4e2c-ab31-cda3f4570642.xml#id-8c8117ec-8fcf-4e2c-ab31-cda3f4570642"/>
  </children>
  <children
      xsi:type="archimate:DiagramModelArchimateObject"
      id="id-61116"
      font="1|Segoe UI|10.0|0|WINDOWS|1|-15|0|0|0|0|0|0|0|0|3|2|1|34|Segoe UI"
      lineColor="#000000"
      fillColor="#daeef3"
      type="1">
    <sourceConnections
        xsi:type="archimate:DiagramModelArchimateConnection"
        id="id-61117"
        font="1|Segoe UI|10.0|0|WINDOWS|1|-15|0|0|0|0|0|0|0|0|3|2|1|34|Segoe UI"
        fontColor="#000000"
        lineColor="#000000"
        source="id-61116"
        target="id-61108">
      <archimateRelationship
          xsi:type="archimate:FlowRelationship"
          href="FlowRelationship_id-53a3adf3-1c4d-4747-9351-cb3130410922.xml#id-53a3adf3-1c4d-4747-9351-cb3130410922"/>
    </sourceConnections>
    <sourceConnections
        xsi:type="archimate:DiagramModelArchimateConnection"
        id="id-61119"
        font="1|Segoe UI|10.0|0|WINDOWS|1|-15|0|0|0|0|0|0|0|0|3|2|1|34|Segoe UI"
        fontColor="#000000"
        lineColor="#000000"
        source="id-61116"
        target="id-61112">
      <bendpoints
          startX="245"
          startY="-23"
          endX="1225"
          endY="437"/>
      <bendpoints
          startX="245"
          startY="-613"
          endX="1225"
          endY="-153"/>
      <bendpoints
          startX="-1021"
          startY="-613"
          endX="-41"
          endY="-153"/>
      <archimateRelationship
          xsi:type="archimate:FlowRelationship"
          href="FlowRelationship_id-56a16205-cd74-46be-944a-4c1e8f559555.xml#id-56a16205-cd74-46be-944a-4c1e8f559555"/>
    </sourceConnections>
    <bounds
        x="1837"
        y="967"
        width="336"
        height="92"/>
    <archimateElement
        xsi:type="archimate:ApplicationComponent"
        href="ApplicationComponent_id-06321658-50d1-4153-b007-6630ffabcd80.xml#id-06321658-50d1-4153-b007-6630ffabcd80"/>
  </children>
  <children
      xsi:type="archimate:DiagramModelArchimateObject"
      id="id-61121"
      targetConnections="id-61105 id-61103 id-61099 id-61125"
      font="1|Segoe UI|10.0|0|WINDOWS|1|-15|0|0|0|0|0|0|0|0|3|2|1|34|Segoe UI"
      lineColor="#000000"
      fillColor="#daeef3"
      type="1">
    <sourceConnections
        xsi:type="archimate:DiagramModelArchimateConnection"
        id="id-61123"
        font="1|Segoe UI|10.0|0|WINDOWS|1|-15|0|0|0|0|0|0|0|0|3|2|1|34|Segoe UI"
        fontColor="#000000"
        lineColor="#000000"
        source="id-61121"
        target="id-61112">
      <bendpoints
          startX="-105"
          startY="-83"
          endX="415"
          endY="-83"/>
      <bendpoints
          startX="-415"
          startY="-83"
          endX="105"
          endY="-83"/>
      <archimateRelationship
          xsi:type="archimate:FlowRelationship"
          href="FlowRelationship_id-030e20d6-0f08-4441-bff3-71f6648c50ff.xml#id-030e20d6-0f08-4441-bff3-71f6648c50ff"/>
    </sourceConnections>
    <bounds
        x="1377"
        y="507"
        width="336"
        height="92"/>
    <archimateElement
        xsi:type="archimate:ApplicationComponent"
        href="ApplicationComponent_id-a97b6545-d5a7-485d-9b13-3ce22db5b9cf.xml#id-a97b6545-d5a7-485d-9b13-3ce22db5b9cf"/>
  </children>
  <children
      xsi:type="archimate:DiagramModelArchimateObject"
      id="id-61092"
      font="1|Segoe UI|10.0|0|WINDOWS|1|-15|0|0|0|0|0|0|0|0|3|2|1|34|Segoe UI"
      lineColor="#000000"
      fillColor="#daeef3"
      type="1">
    <sourceConnections
        xsi:type="archimate:DiagramModelArchimateConnection"
        id="id-61094"
        font="1|Segoe UI|10.0|0|WINDOWS|1|-15|0|0|0|0|0|0|0|0|3|2|1|34|Segoe UI"
        fontColor="#000000"
        lineColor="#000000"
        source="id-61092"
        target="id-61115">
      <archimateRelationship
          xsi:type="archimate:FlowRelationship"
          href="FlowRelationship_id-e5ae1063-2d71-4269-9817-9b8e82da2477.xml#id-e5ae1063-2d71-4269-9817-9b8e82da2477"/>
    </sourceConnections>
    <bounds
        x="1500"
        y="120"
        width="336"
        height="92"/>
    <archimateElement
        xsi:type="archimate:ApplicationComponent"
        href="ApplicationComponent_id-caa38667-222c-48da-8c5e-c643b7a7657a.xml#id-caa38667-222c-48da-8c5e-c643b7a7657a"/>
  </children>
  <children
      xsi:type="archimate:DiagramModelArchimateObject"
      id="id-61096"
      targetConnections="id-61097"
      font="1|Segoe UI|10.0|0|WINDOWS|1|-15|0|0|0|0|0|0|0|0|3|2|1|34|Segoe UI"
      lineColor="#000000"
      fillColor="#daeef3"
      type="1">
    <sourceConnections
        xsi:type="archimate:DiagramModelArchimateConnection"
        id="id-61134"
        font="1|Segoe UI|10.0|0|WINDOWS|1|-15|0|0|0|0|0|0|0|0|3|2|1|34|Segoe UI"
        fontColor="#000000"
        lineColor="#000000"
        source="id-61096"
        target="id-61089">
      <archimateRelationship
          xsi:type="archimate:FlowRelationship"
          href="FlowRelationship_id-af724a93-6795-47a0-8761-a7350001a77a.xml#id-af724a93-6795-47a0-8761-a7350001a77a"/>
    </sourceConnections>
    <bounds
        x="857"
        y="260"
        width="336"
        height="92"/>
    <archimateElement
        xsi:type="archimate:ApplicationComponent"
        href="ApplicationComponent_id-8c2cf498-380a-4fc1-b8ce-becf802d6371.xml#id-8c2cf498-380a-4fc1-b8ce-becf802d6371"/>
  </children>
  <children
      xsi:type="archimate:DiagramModelArchimateObject"
      id="id-61133"
      font="1|Segoe UI|10.0|0|WINDOWS|1|-15|0|0|0|0|0|0|0|0|3|2|1|34|Segoe UI"
      lineColor="#000000"
      fillColor="#daeef3"
      type="1">
    <sourceConnections
        xsi:type="archimate:DiagramModelArchimateConnection"
        id="id-61127"
        font="1|Segoe UI|10.0|0|WINDOWS|1|-15|0|0|0|0|0|0|0|0|3|2|1|34|Segoe UI"
        fontColor="#000000"
        lineColor="#000000"
        source="id-61133"
        target="id-61108">
      <bendpoints
          startX="612"
          startY="7"
          endX="12"
          endY="127"/>
      <archimateRelationship
          xsi:type="archimate:FlowRelationship"
          href="FlowRelationship_id-c3bb17f8-72a4-46c5-8a1b-24ba65874489.xml#id-c3bb17f8-72a4-46c5-8a1b-24ba65874489"/>
    </sourceConnections>
    <bounds
        x="153"
        y="1087"
        width="336"
        height="92"/>
    <archimateElement
        xsi:type="archimate:ApplicationComponent"
        href="ApplicationComponent_id-0f3a945a-02f1-11e6-11ba-005056a85f9c.xml#id-0f3a945a-02f1-11e6-11ba-005056a85f9c"/>
  </children>
  <properties
      key="Object ID"
      value="e31983fd-2ca7-4134-9fda-0a11457c7167"/>
  <properties
      key="Publiceren"
      value="GEMMA Online en redactie"/>
  <properties
      key="Viewtype"
      value="Patroon"/>
  <properties
      key="Architectuurlaag"
      value="Applicatiearchitectuur"/>
  <properties
      key="Domein"
      value="Niet domeingebonden"/>
</archimate:ArchimateDiagramModel>
