<archimate:ArchimateDiagramModel
    xmlns:xsi="http://www.w3.org/2001/XMLSchema-instance"
    xmlns:archimate="http://www.archimatetool.com/archimate"
    name="Toelichting Vergunningenbeheer (VTH-component)"
    id="id-4f80184d-df0c-4c8f-bd76-af5d2e2c54d2">
  <children
      xsi:type="archimate:DiagramModelArchimateObject"
      id="id-29950"
      targetConnections="id-29946"
      font="1|Segoe UI|9.0|0|WINDOWS|1|0|0|0|0|0|0|0|0|1|0|0|0|0|Segoe UI"
      fontColor="#000000"
      lineColor="#000000"
      fillColor="#b7dee8">
    <sourceConnections
        xsi:type="archimate:DiagramModelArchimateConnection"
        id="id-29942"
        font="1|Segoe UI|9.0|0|WINDOWS|1|0|0|0|0|0|0|0|0|1|0|0|0|0|Segoe UI"
        fontColor="#000000"
        lineColor="#000000"
        source="id-29950"
        target="id-29953">
      <archimateRelationship
          xsi:type="archimate:ServingRelationship"
          href="ServingRelationship_id-8baca7d4-925e-40e5-92c1-9ee8ec1ca65b.xml#id-8baca7d4-925e-40e5-92c1-9ee8ec1ca65b"/>
    </sourceConnections>
    <bounds
        x="7"
        y="333"
        width="133"
        height="53"/>
    <archimateElement
        xsi:type="archimate:ApplicationService"
        href="ApplicationService_id-5e67a30544804e998b94ef0a8362cd66.xml#id-5e67a30544804e998b94ef0a8362cd66"/>
  </children>
  <children
      xsi:type="archimate:DiagramModelArchimateObject"
      id="id-29953"
      targetConnections="id-29942 id-29944"
      font="1|Segoe UI|9.0|0|WINDOWS|1|0|0|0|0|0|0|0|0|1|0|0|0|0|Segoe UI"
      fontColor="#000000"
      lineColor="#000000"
      fillColor="#ffffcc">
    <bounds
        x="7"
        y="213"
        width="133"
        height="53"/>
    <archimateElement
        xsi:type="archimate:BusinessFunction"
        href="BusinessFunction_id-7a1e5935-026e-41ef-be95-d02f2a2a3937.xml#id-7a1e5935-026e-41ef-be95-d02f2a2a3937"/>
  </children>
  <children
      xsi:type="archimate:DiagramModelArchimateObject"
      id="id-29956"
      targetConnections="id-29969"
      font="1|Segoe UI|9.0|0|WINDOWS|1|0|0|0|0|0|0|0|0|1|0|0|0|0|Segoe UI"
      fontColor="#000000"
      lineColor="#000000"
      fillColor="#ffffcc">
    <sourceConnections
        xsi:type="archimate:DiagramModelArchimateConnection"
        id="id-29944"
        font="1|Segoe UI|9.0|0|WINDOWS|1|0|0|0|0|0|0|0|0|1|0|0|0|0|Segoe UI"
        fontColor="#000000"
        lineColor="#000000"
        source="id-29956"
        target="id-29953">
      <archimateRelationship
          xsi:type="archimate:AggregationRelationship"
          href="AggregationRelationship_id-5cb443c9-346c-4ecf-aaf4-31f576c8b835.xml#id-5cb443c9-346c-4ecf-aaf4-31f576c8b835"/>
    </sourceConnections>
    <bounds
        x="7"
        y="93"
        width="133"
        height="53"/>
    <archimateElement
        xsi:type="archimate:BusinessFunction"
        href="BusinessFunction_id-9a066e58-f6b8-4761-8159-2f53b2ccf8c7.xml#id-9a066e58-f6b8-4761-8159-2f53b2ccf8c7"/>
  </children>
  <children
      xsi:type="archimate:DiagramModelArchimateObject"
      id="id-29959"
      font="1|Segoe UI|9.0|0|WINDOWS|1|0|0|0|0|0|0|0|0|1|0|0|0|0|Segoe UI"
      fontColor="#000000"
      lineColor="#000000"
      fillColor="#daeef3"
      type="1">
    <sourceConnections
        xsi:type="archimate:DiagramModelArchimateConnection"
        id="id-29946"
        font="1|Segoe UI|9.0|0|WINDOWS|1|0|0|0|0|0|0|0|0|1|0|0|0|0|Segoe UI"
        fontColor="#000000"
        lineColor="#000000"
        source="id-29959"
        target="id-29950">
      <archimateRelationship
          xsi:type="archimate:RealizationRelationship"
          href="RealizationRelationship_id-5414815ad406488c8ca6bb1bda763a5c.xml#id-5414815ad406488c8ca6bb1bda763a5c"/>
    </sourceConnections>
    <sourceConnections
        xsi:type="archimate:DiagramModelArchimateConnection"
        id="id-29957"
        font="1|Segoe UI|9.0|0|WINDOWS|1|0|0|0|0|0|0|0|0|1|0|0|0|0|Segoe UI"
        fontColor="#000000"
        lineColor="#000000"
        source="id-29959"
        target="id-29977">
      <archimateRelationship
          xsi:type="archimate:RealizationRelationship"
          href="RealizationRelationship_id-7aba701dafbc49929cf5a2035236f49b.xml#id-7aba701dafbc49929cf5a2035236f49b"/>
    </sourceConnections>
    <sourceConnections
        xsi:type="archimate:DiagramModelArchimateConnection"
        id="id-29963"
        font="1|Segoe UI|9.0|0|WINDOWS|1|0|0|0|0|0|0|0|0|1|0|0|0|0|Segoe UI"
        fontColor="#000000"
        lineColor="#000000"
        source="id-29959"
        target="id-29974">
      <archimateRelationship
          xsi:type="archimate:RealizationRelationship"
          href="RealizationRelationship_id-408203449ec5424da8c21943a765158b.xml#id-408203449ec5424da8c21943a765158b"/>
    </sourceConnections>
    <sourceConnections
        xsi:type="archimate:DiagramModelArchimateConnection"
        id="id-29954"
        font="1|Segoe UI|9.0|0|WINDOWS|1|0|0|0|0|0|0|0|0|1|0|0|0|0|Segoe UI"
        fontColor="#000000"
        lineColor="#000000"
        source="id-29959"
        target="id-29967">
      <archimateRelationship
          xsi:type="archimate:RealizationRelationship"
          href="RealizationRelationship_id-bc13d7d780f14840bbb9fd98413553d8.xml#id-bc13d7d780f14840bbb9fd98413553d8"/>
    </sourceConnections>
    <sourceConnections
        xsi:type="archimate:DiagramModelArchimateConnection"
        id="id-29960"
        font="1|Segoe UI|9.0|0|WINDOWS|1|0|0|0|0|0|0|0|0|1|0|0|0|0|Segoe UI"
        fontColor="#000000"
        lineColor="#000000"
        source="id-29959"
        target="id-29980">
      <archimateRelationship
          xsi:type="archimate:RealizationRelationship"
          href="RealizationRelationship_id-973b375a355d4472b4e40f225dcc15e8.xml#id-973b375a355d4472b4e40f225dcc15e8"/>
    </sourceConnections>
    <sourceConnections
        xsi:type="archimate:DiagramModelArchimateConnection"
        id="id-30031"
        font="1|Segoe UI|9.0|0|WINDOWS|1|0|0|0|0|0|0|0|0|1|0|0|0|0|Segoe UI"
        fontColor="#000000"
        lineColor="#000000"
        source="id-29959"
        target="id-29937">
      <archimateRelationship
          xsi:type="archimate:RealizationRelationship"
          href="RealizationRelationship_id-df60444074534ae8877dbc08e1a4b68a.xml#id-df60444074534ae8877dbc08e1a4b68a"/>
    </sourceConnections>
    <bounds
        x="133"
        y="533"
        width="133"
        height="53"/>
    <archimateElement
        xsi:type="archimate:ApplicationComponent"
        href="ApplicationComponent_id-ca98dd6d-1c0b-43dc-a26e-61ebd1cd810d.xml#id-ca98dd6d-1c0b-43dc-a26e-61ebd1cd810d"/>
  </children>
  <children
      xsi:type="archimate:DiagramModelArchimateObject"
      id="id-29962"
      targetConnections="id-29948 id-29951"
      font="1|Segoe UI|9.0|0|WINDOWS|1|0|0|0|0|0|0|0|0|1|0|0|0|0|Segoe UI"
      fontColor="#000000"
      lineColor="#000000"
      fillColor="#ffffcc">
    <bounds
        x="247"
        y="214"
        width="133"
        height="53"/>
    <archimateElement
        xsi:type="archimate:BusinessFunction"
        href="BusinessFunction_id-b7e4786e-cff2-40a8-ac4b-6c48a0abfbe0.xml#id-b7e4786e-cff2-40a8-ac4b-6c48a0abfbe0"/>
  </children>
  <children
      xsi:type="archimate:DiagramModelArchimateObject"
      id="id-29967"
      targetConnections="id-29954"
      font="1|Segoe UI|9.0|0|WINDOWS|1|0|0|0|0|0|0|0|0|1|0|0|0|0|Segoe UI"
      fontColor="#000000"
      lineColor="#000000"
      fillColor="#b7dee8">
    <sourceConnections
        xsi:type="archimate:DiagramModelArchimateConnection"
        id="id-29948"
        font="1|Segoe UI|9.0|0|WINDOWS|1|0|0|0|0|0|0|0|0|1|0|0|0|0|Segoe UI"
        fontColor="#000000"
        lineColor="#000000"
        source="id-29967"
        target="id-29962">
      <archimateRelationship
          xsi:type="archimate:ServingRelationship"
          href="ServingRelationship_id-05dfdfdb-87f1-4fbc-b99b-abc673b98272.xml#id-05dfdfdb-87f1-4fbc-b99b-abc673b98272"/>
    </sourceConnections>
    <bounds
        x="247"
        y="333"
        width="133"
        height="53"/>
    <archimateElement
        xsi:type="archimate:ApplicationService"
        href="ApplicationService_id-7ff525cbd3b34e6d98367e768f3eceb4.xml#id-7ff525cbd3b34e6d98367e768f3eceb4"/>
  </children>
  <children
      xsi:type="archimate:DiagramModelArchimateObject"
      id="id-29971"
      targetConnections="id-30019"
      font="1|Segoe UI|9.0|0|WINDOWS|1|0|0|0|0|0|0|0|0|1|0|0|0|0|Segoe UI"
      fontColor="#000000"
      lineColor="#000000"
      fillColor="#ffffcc">
    <sourceConnections
        xsi:type="archimate:DiagramModelArchimateConnection"
        id="id-29951"
        font="1|Segoe UI|9.0|0|WINDOWS|1|0|0|0|0|0|0|0|0|1|0|0|0|0|Segoe UI"
        fontColor="#000000"
        lineColor="#000000"
        source="id-29971"
        target="id-29962">
      <archimateRelationship
          xsi:type="archimate:AggregationRelationship"
          href="AggregationRelationship_id-e9c3ffeb-f96c-4bcd-8e74-cf5c866bb1cc.xml#id-e9c3ffeb-f96c-4bcd-8e74-cf5c866bb1cc"/>
    </sourceConnections>
    <sourceConnections
        xsi:type="archimate:DiagramModelArchimateConnection"
        id="id-29975"
        font="1|Segoe UI|9.0|0|WINDOWS|1|0|0|0|0|0|0|0|0|1|0|0|0|0|Segoe UI"
        fontColor="#000000"
        lineColor="#000000"
        source="id-29971"
        target="id-29992">
      <archimateRelationship
          xsi:type="archimate:AggregationRelationship"
          href="AggregationRelationship_id-e12db515-01d0-4bf5-8283-6db5244e5655.xml#id-e12db515-01d0-4bf5-8283-6db5244e5655"/>
    </sourceConnections>
    <bounds
        x="320"
        y="93"
        width="133"
        height="53"/>
    <archimateElement
        xsi:type="archimate:BusinessFunction"
        href="BusinessFunction_id-2b40d5bc-cd28-4b62-b0b1-a68f16b7aa64.xml#id-2b40d5bc-cd28-4b62-b0b1-a68f16b7aa64"/>
  </children>
  <children
      xsi:type="archimate:DiagramModelArchimateObject"
      id="id-29974"
      targetConnections="id-29963"
      font="1|Segoe UI|9.0|0|WINDOWS|1|0|0|0|0|0|0|0|0|1|0|0|0|0|Segoe UI"
      fontColor="#000000"
      lineColor="#000000"
      fillColor="#b7dee8">
    <sourceConnections
        xsi:type="archimate:DiagramModelArchimateConnection"
        id="id-29985"
        font="1|Segoe UI|9.0|0|WINDOWS|1|0|0|0|0|0|0|0|0|1|0|0|0|0|Segoe UI"
        fontColor="#000000"
        lineColor="#000000"
        source="id-29974"
        target="id-30003">
      <archimateRelationship
          xsi:type="archimate:ServingRelationship"
          href="ServingRelationship_id-73b31472-7d20-467f-9f35-fb6333b36bb1.xml#id-73b31472-7d20-467f-9f35-fb6333b36bb1"/>
    </sourceConnections>
    <sourceConnections
        xsi:type="archimate:DiagramModelArchimateConnection"
        id="id-29988"
        font="1|Segoe UI|9.0|0|WINDOWS|1|0|0|0|0|0|0|0|0|1|0|0|0|0|Segoe UI"
        fontColor="#000000"
        lineColor="#000000"
        source="id-29974"
        target="id-30006">
      <archimateRelationship
          xsi:type="archimate:ServingRelationship"
          href="ServingRelationship_id-f8bc0623-1312-4651-8501-43e3b9d9d13c.xml#id-f8bc0623-1312-4651-8501-43e3b9d9d13c"/>
    </sourceConnections>
    <sourceConnections
        xsi:type="archimate:DiagramModelArchimateConnection"
        id="id-29982"
        font="1|Segoe UI|9.0|0|WINDOWS|1|0|0|0|0|0|0|0|0|1|0|0|0|0|Segoe UI"
        fontColor="#000000"
        lineColor="#000000"
        source="id-29974"
        target="id-29999">
      <archimateRelationship
          xsi:type="archimate:AggregationRelationship"
          href="AggregationRelationship_id-bcbc6707c08a4bf9a2271f4b191ec583.xml#id-bcbc6707c08a4bf9a2271f4b191ec583"/>
    </sourceConnections>
    <sourceConnections
        xsi:type="archimate:DiagramModelArchimateConnection"
        id="id-29978"
        font="1|Segoe UI|9.0|0|WINDOWS|1|0|0|0|0|0|0|0|0|1|0|0|0|0|Segoe UI"
        fontColor="#000000"
        lineColor="#000000"
        source="id-29974"
        target="id-29995">
      <archimateRelationship
          xsi:type="archimate:AggregationRelationship"
          href="AggregationRelationship_id-1050a510f4104020bbf62b5520973880.xml#id-1050a510f4104020bbf62b5520973880"/>
    </sourceConnections>
    <bounds
        x="813"
        y="333"
        width="187"
        height="53"/>
    <archimateElement
        xsi:type="archimate:ApplicationService"
        href="ApplicationService_id-59e3c3ddad2e4ad4a793ffcc0f2ff4e1.xml#id-59e3c3ddad2e4ad4a793ffcc0f2ff4e1"/>
  </children>
  <children
      xsi:type="archimate:DiagramModelArchimateObject"
      id="id-29977"
      targetConnections="id-29957"
      font="1|Segoe UI|9.0|0|WINDOWS|1|0|0|0|0|0|0|0|0|1|0|0|0|0|Segoe UI"
      fontColor="#000000"
      lineColor="#000000"
      fillColor="#b7dee8">
    <sourceConnections
        xsi:type="archimate:DiagramModelArchimateConnection"
        id="id-30010"
        font="1|Segoe UI|9.0|0|WINDOWS|1|0|0|0|0|0|0|0|0|1|0|0|0|0|Segoe UI"
        fontColor="#000000"
        lineColor="#000000"
        source="id-29977"
        target="id-30021">
      <archimateRelationship
          xsi:type="archimate:ServingRelationship"
          href="ServingRelationship_id-6d5989b0-d0c3-4a2f-b0c9-35e8c5fd58b8.xml#id-6d5989b0-d0c3-4a2f-b0c9-35e8c5fd58b8"/>
    </sourceConnections>
    <sourceConnections
        xsi:type="archimate:DiagramModelArchimateConnection"
        id="id-29997"
        font="1|Segoe UI|9.0|0|WINDOWS|1|0|0|0|0|0|0|0|0|1|0|0|0|0|Segoe UI"
        fontColor="#000000"
        lineColor="#000000"
        source="id-29977"
        target="id-30012">
      <archimateRelationship
          xsi:type="archimate:AggregationRelationship"
          href="AggregationRelationship_id-b06739c99eba4febac261ec991410b3d.xml#id-b06739c99eba4febac261ec991410b3d"/>
    </sourceConnections>
    <sourceConnections
        xsi:type="archimate:DiagramModelArchimateConnection"
        id="id-30001"
        font="1|Segoe UI|9.0|0|WINDOWS|1|0|0|0|0|0|0|0|0|1|0|0|0|0|Segoe UI"
        fontColor="#000000"
        lineColor="#000000"
        source="id-29977"
        target="id-30033">
      <archimateRelationship
          xsi:type="archimate:AggregationRelationship"
          href="AggregationRelationship_id-4931133cff354de29752b7e2c2f66780.xml#id-4931133cff354de29752b7e2c2f66780"/>
    </sourceConnections>
    <bounds
        x="1167"
        y="333"
        width="187"
        height="53"/>
    <archimateElement
        xsi:type="archimate:ApplicationService"
        href="ApplicationService_id-a16facc13efd493d9fe3d8af65ef82fa.xml#id-a16facc13efd493d9fe3d8af65ef82fa"/>
  </children>
  <children
      xsi:type="archimate:DiagramModelArchimateObject"
      id="id-29980"
      targetConnections="id-29960"
      font="1|Segoe UI|9.0|0|WINDOWS|1|0|0|0|0|0|0|0|0|1|0|0|0|0|Segoe UI"
      fontColor="#000000"
      lineColor="#000000"
      fillColor="#b7dee8">
    <sourceConnections
        xsi:type="archimate:DiagramModelArchimateConnection"
        id="id-29972"
        font="1|Segoe UI|9.0|0|WINDOWS|1|0|0|0|0|0|0|0|0|1|0|0|0|0|Segoe UI"
        fontColor="#000000"
        lineColor="#000000"
        source="id-29980"
        target="id-29992">
      <archimateRelationship
          xsi:type="archimate:ServingRelationship"
          href="ServingRelationship_id-c79bccc7-e91b-4714-b5c5-f5a04f4469e1.xml#id-c79bccc7-e91b-4714-b5c5-f5a04f4469e1"/>
    </sourceConnections>
    <bounds
        x="393"
        y="333"
        width="133"
        height="53"/>
    <archimateElement
        xsi:type="archimate:ApplicationService"
        href="ApplicationService_id-426d0f7cc8bb4012bfa79e9a71322ab2.xml#id-426d0f7cc8bb4012bfa79e9a71322ab2"/>
  </children>
  <children
      xsi:type="archimate:DiagramModelArchimateObject"
      id="id-29984"
      targetConnections="id-29965"
      font="1|Segoe UI|9.0|0|WINDOWS|1|0|0|0|0|0|0|0|0|1|0|0|0|0|Segoe UI"
      fontColor="#000000"
      lineColor="#000000"
      fillColor="#ffffcc">
    <bounds
        x="153"
        y="93"
        width="133"
        height="53"/>
    <archimateElement
        xsi:type="archimate:BusinessFunction"
        href="BusinessFunction_id-3d875d2f-8411-4bad-9427-2b6f7d19b014.xml#id-3d875d2f-8411-4bad-9427-2b6f7d19b014"/>
  </children>
  <children
      xsi:type="archimate:DiagramModelArchimateObject"
      id="id-29987"
      font="1|Segoe UI|9.0|0|WINDOWS|1|0|0|0|0|0|0|0|0|1|0|0|0|0|Segoe UI"
      fontColor="#000000"
      lineColor="#000000"
      fillColor="#ffffcc">
    <sourceConnections
        xsi:type="archimate:DiagramModelArchimateConnection"
        id="id-29965"
        font="1|Segoe UI|9.0|0|WINDOWS|1|0|0|0|0|0|0|0|0|1|0|0|0|0|Segoe UI"
        fontColor="#000000"
        lineColor="#000000"
        source="id-29987"
        target="id-29984">
      <archimateRelationship
          xsi:type="archimate:AggregationRelationship"
          href="AggregationRelationship_id-b0c3e25f-fd3e-42c2-ab67-058ef98147ee.xml#id-b0c3e25f-fd3e-42c2-ab67-058ef98147ee"/>
    </sourceConnections>
    <sourceConnections
        xsi:type="archimate:DiagramModelArchimateConnection"
        id="id-29969"
        font="1|Segoe UI|9.0|0|WINDOWS|1|0|0|0|0|0|0|0|0|1|0|0|0|0|Segoe UI"
        fontColor="#000000"
        lineColor="#000000"
        source="id-29987"
        target="id-29956">
      <archimateRelationship
          xsi:type="archimate:AggregationRelationship"
          href="AggregationRelationship_id-abf62f00-46ee-4865-a01e-141b51a507c1.xml#id-abf62f00-46ee-4865-a01e-141b51a507c1"/>
    </sourceConnections>
    <bounds
        x="80"
        y="7"
        width="133"
        height="53"/>
    <archimateElement
        xsi:type="archimate:BusinessFunction"
        href="BusinessFunction_id-f10ff76e-e4de-4f30-bb1f-81c7cfffb46a.xml#id-f10ff76e-e4de-4f30-bb1f-81c7cfffb46a"/>
  </children>
  <children
      xsi:type="archimate:DiagramModelArchimateObject"
      id="id-29992"
      targetConnections="id-29972 id-29975"
      font="1|Segoe UI|9.0|0|WINDOWS|1|0|0|0|0|0|0|0|0|1|0|0|0|0|Segoe UI"
      fontColor="#000000"
      lineColor="#000000"
      fillColor="#ffffcc">
    <bounds
        x="393"
        y="213"
        width="133"
        height="53"/>
    <archimateElement
        xsi:type="archimate:BusinessFunction"
        href="BusinessFunction_id-5c098c43-1d67-4848-bc56-fe53311e569f.xml#id-5c098c43-1d67-4848-bc56-fe53311e569f"/>
  </children>
  <children
      xsi:type="archimate:DiagramModelArchimateObject"
      id="id-29995"
      targetConnections="id-29978"
      font="1|Segoe UI|9.0|0|WINDOWS|1|0|0|0|0|0|0|0|0|1|0|0|0|0|Segoe UI"
      fontColor="#000000"
      lineColor="#000000"
      fillColor="#b7dee8">
    <bounds
        x="760"
        y="480"
        width="133"
        height="53"/>
    <archimateElement
        xsi:type="archimate:ApplicationService"
        href="ApplicationService_id-94036783f3b0499980030bbb2a3171a0.xml#id-94036783f3b0499980030bbb2a3171a0"/>
  </children>
  <children
      xsi:type="archimate:DiagramModelArchimateObject"
      id="id-29999"
      targetConnections="id-29982"
      font="1|Segoe UI|9.0|0|WINDOWS|1|0|0|0|0|0|0|0|0|1|0|0|0|0|Segoe UI"
      fontColor="#000000"
      lineColor="#000000"
      fillColor="#b7dee8">
    <bounds
        x="907"
        y="480"
        width="133"
        height="53"/>
    <archimateElement
        xsi:type="archimate:ApplicationService"
        href="ApplicationService_id-090b41cf14df41d8bcafbe4aba7299dc.xml#id-090b41cf14df41d8bcafbe4aba7299dc"/>
  </children>
  <children
      xsi:type="archimate:DiagramModelArchimateObject"
      id="id-30003"
      targetConnections="id-29985 id-29990"
      font="1|Segoe UI|9.0|0|WINDOWS|1|0|0|0|0|0|0|0|0|1|0|0|0|0|Segoe UI"
      fontColor="#000000"
      lineColor="#000000"
      fillColor="#ffffcc">
    <bounds
        x="767"
        y="213"
        width="133"
        height="53"/>
    <archimateElement
        xsi:type="archimate:BusinessFunction"
        href="BusinessFunction_id-27112fc9-9263-4c21-95e5-554e41da8e40.xml#id-27112fc9-9263-4c21-95e5-554e41da8e40"/>
  </children>
  <children
      xsi:type="archimate:DiagramModelArchimateObject"
      id="id-30006"
      targetConnections="id-29988 id-29993"
      font="1|Segoe UI|9.0|0|WINDOWS|1|0|0|0|0|0|0|0|0|1|0|0|0|0|Segoe UI"
      fontColor="#000000"
      lineColor="#000000"
      fillColor="#ffffcc">
    <bounds
        x="913"
        y="213"
        width="133"
        height="53"/>
    <archimateElement
        xsi:type="archimate:BusinessFunction"
        href="BusinessFunction_id-173177ab-9277-4146-ad60-24159bb6b974.xml#id-173177ab-9277-4146-ad60-24159bb6b974"/>
  </children>
  <children
      xsi:type="archimate:DiagramModelArchimateObject"
      id="id-30009"
      targetConnections="id-30016"
      font="1|Segoe UI|9.0|0|WINDOWS|1|0|0|0|0|0|0|0|0|1|0|0|0|0|Segoe UI"
      fontColor="#000000"
      lineColor="#000000"
      fillColor="#ffffcc">
    <sourceConnections
        xsi:type="archimate:DiagramModelArchimateConnection"
        id="id-29990"
        font="1|Segoe UI|9.0|0|WINDOWS|1|0|0|0|0|0|0|0|0|1|0|0|0|0|Segoe UI"
        fontColor="#000000"
        lineColor="#000000"
        source="id-30009"
        target="id-30003">
      <archimateRelationship
          xsi:type="archimate:AggregationRelationship"
          href="AggregationRelationship_id-2826bed7-2250-478d-82e7-a537a0490b39.xml#id-2826bed7-2250-478d-82e7-a537a0490b39"/>
    </sourceConnections>
    <sourceConnections
        xsi:type="archimate:DiagramModelArchimateConnection"
        id="id-29993"
        font="1|Segoe UI|9.0|0|WINDOWS|1|0|0|0|0|0|0|0|0|1|0|0|0|0|Segoe UI"
        fontColor="#000000"
        lineColor="#000000"
        source="id-30009"
        target="id-30006">
      <archimateRelationship
          xsi:type="archimate:AggregationRelationship"
          href="AggregationRelationship_id-3eee5016-6dfb-49ba-b95f-29455ab77b38.xml#id-3eee5016-6dfb-49ba-b95f-29455ab77b38"/>
    </sourceConnections>
    <bounds
        x="840"
        y="93"
        width="133"
        height="53"/>
    <archimateElement
        xsi:type="archimate:BusinessFunction"
        href="BusinessFunction_id-11ceda47-d0a4-49cb-88d7-eaf623172f3f.xml#id-11ceda47-d0a4-49cb-88d7-eaf623172f3f"/>
  </children>
  <children
      xsi:type="archimate:DiagramModelArchimateObject"
      id="id-30012"
      targetConnections="id-29997"
      font="1|Segoe UI|9.0|0|WINDOWS|1|0|0|0|0|0|0|0|0|1|0|0|0|0|Segoe UI"
      fontColor="#000000"
      lineColor="#000000"
      fillColor="#b7dee8">
    <bounds
        x="1080"
        y="480"
        width="187"
        height="53"/>
    <archimateElement
        xsi:type="archimate:ApplicationService"
        href="ApplicationService_id-d683de091b11446bbeb1b67bb096f30f.xml#id-d683de091b11446bbeb1b67bb096f30f"/>
  </children>
  <children
      xsi:type="archimate:DiagramModelArchimateObject"
      id="id-30018"
      targetConnections="id-30014"
      font="1|Segoe UI|9.0|0|WINDOWS|1|0|0|0|0|0|0|0|0|1|0|0|0|0|Segoe UI"
      fontColor="#000000"
      lineColor="#000000"
      fillColor="#ffffcc">
    <sourceConnections
        xsi:type="archimate:DiagramModelArchimateConnection"
        id="id-30004"
        font="1|Segoe UI|9.0|0|WINDOWS|1|0|0|0|0|0|0|0|0|1|0|0|0|0|Segoe UI"
        fontColor="#000000"
        lineColor="#000000"
        source="id-30018"
        target="id-30024">
      <archimateRelationship
          xsi:type="archimate:AggregationRelationship"
          href="AggregationRelationship_id-415d1bc4-0c9e-461f-8be0-55578db62843.xml#id-415d1bc4-0c9e-461f-8be0-55578db62843"/>
    </sourceConnections>
    <sourceConnections
        xsi:type="archimate:DiagramModelArchimateConnection"
        id="id-30007"
        font="1|Segoe UI|9.0|0|WINDOWS|1|0|0|0|0|0|0|0|0|1|0|0|0|0|Segoe UI"
        fontColor="#000000"
        lineColor="#000000"
        source="id-30018"
        target="id-30021">
      <archimateRelationship
          xsi:type="archimate:AggregationRelationship"
          href="AggregationRelationship_id-551f9497-3d14-4d0d-86bf-1906d7790804.xml#id-551f9497-3d14-4d0d-86bf-1906d7790804"/>
    </sourceConnections>
    <bounds
        x="1180"
        y="93"
        width="133"
        height="53"/>
    <archimateElement
        xsi:type="archimate:BusinessFunction"
        href="BusinessFunction_id-73b339b1-aa26-4282-8556-a497956efd7d.xml#id-73b339b1-aa26-4282-8556-a497956efd7d"/>
  </children>
  <children
      xsi:type="archimate:DiagramModelArchimateObject"
      id="id-30021"
      targetConnections="id-30007 id-30010"
      font="1|Segoe UI|9.0|0|WINDOWS|1|0|0|0|0|0|0|0|0|1|0|0|0|0|Segoe UI"
      fontColor="#000000"
      lineColor="#000000"
      fillColor="#ffffcc">
    <bounds
        x="1107"
        y="213"
        width="133"
        height="53"/>
    <archimateElement
        xsi:type="archimate:BusinessFunction"
        href="BusinessFunction_id-020f2f8c-d549-4a95-a2a9-56c1b0a43be8.xml#id-020f2f8c-d549-4a95-a2a9-56c1b0a43be8"/>
  </children>
  <children
      xsi:type="archimate:DiagramModelArchimateObject"
      id="id-30024"
      targetConnections="id-30004"
      font="1|Segoe UI|9.0|0|WINDOWS|1|0|0|0|0|0|0|0|0|1|0|0|0|0|Segoe UI"
      fontColor="#000000"
      lineColor="#000000"
      fillColor="#ffffcc">
    <bounds
        x="1260"
        y="213"
        width="133"
        height="53"/>
    <archimateElement
        xsi:type="archimate:BusinessFunction"
        href="BusinessFunction_id-aac7ff27-3c79-4234-bf48-1cc00e450553.xml#id-aac7ff27-3c79-4234-bf48-1cc00e450553"/>
  </children>
  <children
      xsi:type="archimate:DiagramModelArchimateObject"
      id="id-30027"
      font="1|Segoe UI|9.0|0|WINDOWS|1|0|0|0|0|0|0|0|0|1|0|0|0|0|Segoe UI"
      fontColor="#000000"
      lineColor="#000000"
      fillColor="#ffffcc">
    <sourceConnections
        xsi:type="archimate:DiagramModelArchimateConnection"
        id="id-30014"
        font="1|Segoe UI|9.0|0|WINDOWS|1|0|0|0|0|0|0|0|0|1|0|0|0|0|Segoe UI"
        fontColor="#000000"
        lineColor="#000000"
        source="id-30027"
        target="id-30018">
      <archimateRelationship
          xsi:type="archimate:AggregationRelationship"
          href="AggregationRelationship_id-03867c25-1223-4af3-8e16-deda2c621692.xml#id-03867c25-1223-4af3-8e16-deda2c621692"/>
    </sourceConnections>
    <sourceConnections
        xsi:type="archimate:DiagramModelArchimateConnection"
        id="id-30016"
        font="1|Segoe UI|9.0|0|WINDOWS|1|0|0|0|0|0|0|0|0|1|0|0|0|0|Segoe UI"
        fontColor="#000000"
        lineColor="#000000"
        source="id-30027"
        target="id-30009">
      <archimateRelationship
          xsi:type="archimate:AggregationRelationship"
          href="AggregationRelationship_id-aaa45392-d081-4a55-97d9-698db0f4934f.xml#id-aaa45392-d081-4a55-97d9-698db0f4934f"/>
    </sourceConnections>
    <bounds
        x="987"
        y="7"
        width="133"
        height="53"/>
    <archimateElement
        xsi:type="archimate:BusinessFunction"
        href="BusinessFunction_id-de168a10-7030-4026-bd95-298e6a6cb3e2.xml#id-de168a10-7030-4026-bd95-298e6a6cb3e2"/>
  </children>
  <children
      xsi:type="archimate:DiagramModelArchimateObject"
      id="id-30030"
      font="1|Segoe UI|9.0|0|WINDOWS|1|0|0|0|0|0|0|0|0|1|0|0|0|0|Segoe UI"
      fontColor="#000000"
      lineColor="#000000"
      fillColor="#ffffcc">
    <sourceConnections
        xsi:type="archimate:DiagramModelArchimateConnection"
        id="id-30019"
        font="1|Segoe UI|9.0|0|WINDOWS|1|0|0|0|0|0|0|0|0|1|0|0|0|0|Segoe UI"
        fontColor="#000000"
        lineColor="#000000"
        source="id-30030"
        target="id-29971">
      <archimateRelationship
          xsi:type="archimate:AggregationRelationship"
          href="AggregationRelationship_id-ec3df199-3782-479d-874e-73b99b31262b.xml#id-ec3df199-3782-479d-874e-73b99b31262b"/>
    </sourceConnections>
    <bounds
        x="320"
        y="7"
        width="133"
        height="53"/>
    <archimateElement
        xsi:type="archimate:BusinessFunction"
        href="BusinessFunction_id-f54b116c-22f4-4f01-bf6d-997debf536c3.xml#id-f54b116c-22f4-4f01-bf6d-997debf536c3"/>
  </children>
  <children
      xsi:type="archimate:DiagramModelArchimateObject"
      id="id-30033"
      targetConnections="id-30001"
      font="1|Segoe UI|9.0|0|WINDOWS|1|0|0|0|0|0|0|0|0|1|0|0|0|0|Segoe UI"
      fontColor="#000000"
      lineColor="#000000"
      fillColor="#b7dee8">
    <bounds
        x="1280"
        y="480"
        width="187"
        height="53"/>
    <archimateElement
        xsi:type="archimate:ApplicationService"
        href="ApplicationService_id-a21a725fb103475d9d848569fbe49a60.xml#id-a21a725fb103475d9d848569fbe49a60"/>
  </children>
  <children
      xsi:type="archimate:DiagramModelArchimateObject"
      id="id-29937"
      targetConnections="id-30031"
      font="1|Segoe UI|9.0|0|WINDOWS|1|0|0|0|0|0|0|0|0|1|0|0|0|0|Segoe UI"
      fontColor="#000000"
      lineColor="#000000"
      fillColor="#b7dee8">
    <sourceConnections
        xsi:type="archimate:DiagramModelArchimateConnection"
        id="id-30022"
        font="1|Segoe UI|9.0|0|WINDOWS|1|0|0|0|0|0|0|0|0|1|0|0|0|0|Segoe UI"
        fontColor="#000000"
        lineColor="#000000"
        source="id-29937"
        target="id-29940">
      <archimateRelationship
          xsi:type="archimate:ServingRelationship"
          href="ServingRelationship_id-11bca407-e2f0-4598-9b30-516c3feedac8.xml#id-11bca407-e2f0-4598-9b30-516c3feedac8"/>
    </sourceConnections>
    <bounds
        x="583"
        y="333"
        width="133"
        height="53"/>
    <archimateElement
        xsi:type="archimate:ApplicationService"
        href="ApplicationService_id-ea8fbe41a5344c84a414de606824b40f.xml#id-ea8fbe41a5344c84a414de606824b40f"/>
  </children>
  <children
      xsi:type="archimate:DiagramModelArchimateObject"
      id="id-29939"
      targetConnections="id-30028"
      font="1|Segoe UI|9.0|0|WINDOWS|1|0|0|0|0|0|0|0|0|1|0|0|0|0|Segoe UI"
      fontColor="#000000"
      lineColor="#000000"
      fillColor="#ffffcc">
    <sourceConnections
        xsi:type="archimate:DiagramModelArchimateConnection"
        id="id-30025"
        font="1|Segoe UI|9.0|0|WINDOWS|1|0|0|0|0|0|0|0|0|1|0|0|0|0|Segoe UI"
        fontColor="#000000"
        lineColor="#000000"
        source="id-29939"
        target="id-29940">
      <archimateRelationship
          xsi:type="archimate:AggregationRelationship"
          href="AggregationRelationship_id-bfa5284b-00ed-4a12-9f78-48dfc65a8fab.xml#id-bfa5284b-00ed-4a12-9f78-48dfc65a8fab"/>
    </sourceConnections>
    <bounds
        x="583"
        y="93"
        width="133"
        height="53"/>
    <archimateElement
        xsi:type="archimate:BusinessFunction"
        href="BusinessFunction_id-4240888f-8b62-45b3-9dcc-aca35a71e2a6.xml#id-4240888f-8b62-45b3-9dcc-aca35a71e2a6"/>
  </children>
  <children
      xsi:type="archimate:DiagramModelArchimateObject"
      id="id-29940"
      targetConnections="id-30022 id-30025"
      font="1|Segoe UI|9.0|0|WINDOWS|1|0|0|0|0|0|0|0|0|1|0|0|0|0|Segoe UI"
      fontColor="#000000"
      lineColor="#000000"
      fillColor="#ffffcc">
    <bounds
        x="583"
        y="213"
        width="133"
        height="53"/>
    <archimateElement
        xsi:type="archimate:BusinessFunction"
        href="BusinessFunction_id-3921d4fb-1a96-4933-92ee-105a231bd21d.xml#id-3921d4fb-1a96-4933-92ee-105a231bd21d"/>
  </children>
  <children
      xsi:type="archimate:DiagramModelArchimateObject"
      id="id-29941"
      font="1|Segoe UI|9.0|0|WINDOWS|1|0|0|0|0|0|0|0|0|1|0|0|0|0|Segoe UI"
      fontColor="#000000"
      lineColor="#000000"
      fillColor="#ffffcc">
    <sourceConnections
        xsi:type="archimate:DiagramModelArchimateConnection"
        id="id-30028"
        font="1|Segoe UI|9.0|0|WINDOWS|1|0|0|0|0|0|0|0|0|1|0|0|0|0|Segoe UI"
        fontColor="#000000"
        lineColor="#000000"
        source="id-29941"
        target="id-29939">
      <archimateRelationship
          xsi:type="archimate:AggregationRelationship"
          href="AggregationRelationship_id-704abec0-6de4-4a3c-a171-34c01a84a26d.xml#id-704abec0-6de4-4a3c-a171-34c01a84a26d"/>
    </sourceConnections>
    <bounds
        x="583"
        y="7"
        width="133"
        height="53"/>
    <archimateElement
        xsi:type="archimate:BusinessFunction"
        href="BusinessFunction_id-524bf2df-191c-48a5-9a60-ab9526a38fb6.xml#id-524bf2df-191c-48a5-9a60-ab9526a38fb6"/>
  </children>
  <properties
      key="Architectuurlaag"
      value="Totaal (meerlaags)"/>
  <properties
      key="Domein"
      value="Niet domeingebonden"/>
  <properties
      key="Object ID"
      value="4f80184d-df0c-4c8f-bd76-af5d2e2c54d2"/>
  <properties
      key="Detailniveau"
      value="Samenhang"/>
  <properties
      key="Publiceren"
      value="Niet"/>
  <properties
      key="Scope"
      value="Gemeente"/>
  <properties
      key="Viewtype"
      value="Toelichting"/>
  <properties
      key="GEMMA thema"
      value="Geen"/>
</archimate:ArchimateDiagramModel>
