<archimate:ArchimateDiagramModel
    xmlns:xsi="http://www.w3.org/2001/XMLSchema-instance"
    xmlns:archimate="http://www.archimatetool.com/archimate"
    name="GR02 Domeingroepen bedrijfsfunctiemodel"
    id="id-26491">
  <children
      xsi:type="archimate:DiagramModelArchimateObject"
      id="id-38597"
      font="1|Arial|14.0|0|WINDOWS|1|0|0|0|0|0|0|0|0|1|0|0|0|0|Arial"
      fontColor="#000000"
      lineColor="#000000"
      textAlignment="1"
      fillColor="#ffe0e0">
    <sourceConnections
        xsi:type="archimate:DiagramModelArchimateConnection"
        id="id-38542"
        font="1|Arial|10.0|0|WINDOWS|1|0|0|0|0|0|0|0|0|1|0|0|0|0|Arial"
        fontColor="#000000"
        lineColor="#000000"
        source="id-38597"
        target="id-38534">
      <archimateRelationship
          xsi:type="archimate:AggregationRelationship"
          href="AggregationRelationship_id-38543.xml#id-38543"/>
    </sourceConnections>
    <sourceConnections
        xsi:type="archimate:DiagramModelArchimateConnection"
        id="id-38572"
        font="1|Arial|10.0|0|WINDOWS|1|0|0|0|0|0|0|0|0|1|0|0|0|0|Arial"
        fontColor="#000000"
        lineColor="#000000"
        source="id-38597"
        target="id-38552">
      <archimateRelationship
          xsi:type="archimate:AggregationRelationship"
          href="AggregationRelationship_id-38573.xml#id-38573"/>
    </sourceConnections>
    <bounds
        x="1160"
        y="1160"
        width="347"
        height="89"/>
    <archimateElement
        xsi:type="archimate:Grouping"
        href="Grouping_id-29041.xml#id-29041"/>
  </children>
  <children
      xsi:type="archimate:DiagramModelArchimateObject"
      id="id-38600"
      font="1|Arial|14.0|0|WINDOWS|1|0|0|0|0|0|0|0|0|1|0|0|0|0|Arial"
      fontColor="#000000"
      lineColor="#000000"
      textAlignment="1"
      fillColor="#ffe0e0">
    <sourceConnections
        xsi:type="archimate:DiagramModelArchimateConnection"
        id="id-38553"
        font="1|Arial|10.0|0|WINDOWS|1|0|0|0|0|0|0|0|0|1|0|0|0|0|Arial"
        fontColor="#000000"
        lineColor="#000000"
        source="id-38600"
        target="id-38511">
      <archimateRelationship
          xsi:type="archimate:AggregationRelationship"
          href="AggregationRelationship_id-38554.xml#id-38554"/>
    </sourceConnections>
    <sourceConnections
        xsi:type="archimate:DiagramModelArchimateConnection"
        id="id-38557"
        font="1|Arial|10.0|0|WINDOWS|1|0|0|0|0|0|0|0|0|1|0|0|0|0|Arial"
        fontColor="#000000"
        lineColor="#000000"
        source="id-38600"
        target="id-38525">
      <archimateRelationship
          xsi:type="archimate:AggregationRelationship"
          href="AggregationRelationship_id-38558.xml#id-38558"/>
    </sourceConnections>
    <bounds
        x="53"
        y="1160"
        width="347"
        height="89"/>
    <archimateElement
        xsi:type="archimate:Grouping"
        href="Grouping_id-35614.xml#id-35614"/>
  </children>
  <children
      xsi:type="archimate:DiagramModelArchimateObject"
      id="id-38494"
      font="1|Arial|14.0|0|WINDOWS|1|0|0|0|0|0|0|0|0|1|0|0|0|0|Arial"
      fontColor="#000000"
      lineColor="#000000"
      textAlignment="1"
      fillColor="#ffe0e0">
    <sourceConnections
        xsi:type="archimate:DiagramModelArchimateConnection"
        id="id-38546"
        font="1|Arial|10.0|0|WINDOWS|1|0|0|0|0|0|0|0|0|1|0|0|0|0|Arial"
        fontColor="#000000"
        lineColor="#000000"
        source="id-38494"
        target="id-38526">
      <archimateRelationship
          xsi:type="archimate:AggregationRelationship"
          href="AggregationRelationship_id-38547.xml#id-38547"/>
    </sourceConnections>
    <sourceConnections
        xsi:type="archimate:DiagramModelArchimateConnection"
        id="id-38549"
        font="1|Arial|10.0|0|WINDOWS|1|0|0|0|0|0|0|0|0|1|0|0|0|0|Arial"
        fontColor="#000000"
        lineColor="#000000"
        source="id-38494"
        target="id-38523">
      <archimateRelationship
          xsi:type="archimate:AggregationRelationship"
          href="AggregationRelationship_id-38550.xml#id-38550"/>
    </sourceConnections>
    <bounds
        x="427"
        y="1160"
        width="347"
        height="89"/>
    <archimateElement
        xsi:type="archimate:Grouping"
        href="Grouping_id-35618.xml#id-35618"/>
  </children>
  <children
      xsi:type="archimate:DiagramModelArchimateObject"
      id="id-38497"
      font="1|Arial|14.0|0|WINDOWS|1|0|0|0|0|0|0|0|0|1|0|0|0|0|Arial"
      fontColor="#000000"
      lineColor="#000000"
      textAlignment="1"
      fillColor="#ffe0e0">
    <sourceConnections
        xsi:type="archimate:DiagramModelArchimateConnection"
        id="id-38561"
        font="1|Arial|10.0|0|WINDOWS|1|0|0|0|0|0|0|0|0|1|0|0|0|0|Arial"
        fontColor="#000000"
        lineColor="#000000"
        source="id-38497"
        target="id-38578">
      <archimateRelationship
          xsi:type="archimate:AggregationRelationship"
          href="AggregationRelationship_id-38562.xml#id-38562"/>
    </sourceConnections>
    <sourceConnections
        xsi:type="archimate:DiagramModelArchimateConnection"
        id="id-38565"
        font="1|Arial|10.0|0|WINDOWS|1|0|0|0|0|0|0|0|0|1|0|0|0|0|Arial"
        fontColor="#000000"
        lineColor="#000000"
        source="id-38497"
        target="id-38530">
      <archimateRelationship
          xsi:type="archimate:AggregationRelationship"
          href="AggregationRelationship_id-38566.xml#id-38566"/>
    </sourceConnections>
    <sourceConnections
        xsi:type="archimate:DiagramModelArchimateConnection"
        id="id-38569"
        font="1|Arial|10.0|0|WINDOWS|1|0|0|0|0|0|0|0|0|1|0|0|0|0|Arial"
        fontColor="#000000"
        lineColor="#000000"
        source="id-38497"
        target="id-38538">
      <archimateRelationship
          xsi:type="archimate:AggregationRelationship"
          href="AggregationRelationship_id-38570.xml#id-38570"/>
    </sourceConnections>
    <bounds
        x="793"
        y="1160"
        width="347"
        height="89"/>
    <archimateElement
        xsi:type="archimate:Grouping"
        href="Grouping_id-35622.xml#id-35622"/>
  </children>
  <children
      xsi:type="archimate:DiagramModelArchimateObject"
      id="id-38500"
      font="1|Arial|10.0|0|WINDOWS|1|0|0|0|0|0|0|0|0|1|0|0|0|0|Arial"
      fontColor="#000000"
      lineColor="#000000"
      textAlignment="1"
      fillColor="#ffe0e0">
    <sourceConnections
        xsi:type="archimate:DiagramModelArchimateConnection"
        id="id-38527"
        font="1|Arial|10.0|0|WINDOWS|1|0|0|0|0|0|0|0|0|1|0|0|0|0|Arial"
        fontColor="#000000"
        lineColor="#000000"
        source="id-38500"
        target="id-38508">
      <archimateRelationship
          xsi:type="archimate:AggregationRelationship"
          href="AggregationRelationship_id-38528.xml#id-38528"/>
    </sourceConnections>
    <sourceConnections
        xsi:type="archimate:DiagramModelArchimateConnection"
        id="id-38531"
        font="1|Arial|10.0|0|WINDOWS|1|0|0|0|0|0|0|0|0|1|0|0|0|0|Arial"
        fontColor="#000000"
        lineColor="#000000"
        source="id-38500"
        target="id-38590">
      <archimateRelationship
          xsi:type="archimate:AggregationRelationship"
          href="AggregationRelationship_id-38532.xml#id-38532"/>
    </sourceConnections>
    <sourceConnections
        xsi:type="archimate:DiagramModelArchimateConnection"
        id="id-38535"
        font="1|Arial|10.0|0|WINDOWS|1|0|0|0|0|0|0|0|0|1|0|0|0|0|Arial"
        fontColor="#000000"
        lineColor="#000000"
        source="id-38500"
        target="id-38574">
      <archimateRelationship
          xsi:type="archimate:AggregationRelationship"
          href="AggregationRelationship_id-38536.xml#id-38536"/>
    </sourceConnections>
    <sourceConnections
        xsi:type="archimate:DiagramModelArchimateConnection"
        id="id-38539"
        font="1|Arial|10.0|0|WINDOWS|1|0|0|0|0|0|0|0|0|1|0|0|0|0|Arial"
        fontColor="#000000"
        lineColor="#000000"
        source="id-38500"
        target="id-38544">
      <archimateRelationship
          xsi:type="archimate:AggregationRelationship"
          href="AggregationRelationship_id-38540.xml#id-38540"/>
    </sourceConnections>
    <bounds
        x="1667"
        y="647"
        width="304"
        height="89"/>
    <archimateElement
        xsi:type="archimate:Grouping"
        href="Grouping_id-35740.xml#id-35740"/>
  </children>
  <children
      xsi:type="archimate:DiagramModelArchimateObject"
      id="id-38503"
      targetConnections="id-38575"
      font="1|Arial|10.0|0|WINDOWS|1|0|0|0|0|0|0|0|0|1|0|0|0|0|Arial"
      fontColor="#000000"
      lineColor="#000000"
      fillColor="#fff29b">
    <sourceConnections
        xsi:type="archimate:DiagramModelArchimateConnection"
        id="5ff49513-8e12-440a-92ec-0896bfe18237"
        source="id-38503"
        target="id-38504">
      <archimateRelationship
          xsi:type="archimate:AggregationRelationship"
          href="AggregationRelationship_id-35205.xml#id-35205"/>
    </sourceConnections>
    <sourceConnections
        xsi:type="archimate:DiagramModelArchimateConnection"
        id="cbd40c45-29d0-4f44-82d3-1ff67e2c8865"
        source="id-38503"
        target="id-38507">
      <archimateRelationship
          xsi:type="archimate:AggregationRelationship"
          href="AggregationRelationship_id-29595.xml#id-29595"/>
    </sourceConnections>
    <sourceConnections
        xsi:type="archimate:DiagramModelArchimateConnection"
        id="384096f4-10b2-4c40-b5e4-98fe28a27cad"
        source="id-38503"
        target="id-38510">
      <archimateRelationship
          xsi:type="archimate:AggregationRelationship"
          href="AggregationRelationship_id-35201.xml#id-35201"/>
    </sourceConnections>
    <sourceConnections
        xsi:type="archimate:DiagramModelArchimateConnection"
        id="6da655bc-5e56-44f0-a0ce-962c8a7bb470"
        source="id-38503"
        target="id-38514">
      <archimateRelationship
          xsi:type="archimate:AggregationRelationship"
          href="AggregationRelationship_id-35198.xml#id-35198"/>
    </sourceConnections>
    <bounds
        x="47"
        y="40"
        width="1480"
        height="87"/>
    <children
        xsi:type="archimate:DiagramModelArchimateObject"
        id="id-38504"
        targetConnections="5ff49513-8e12-440a-92ec-0896bfe18237"
        font="1|Arial|10.0|0|WINDOWS|1|0|0|0|0|0|0|0|0|1|0|0|0|0|Arial"
        fontColor="#000000"
        lineColor="#000000"
        fillColor="#ffffcc">
      <bounds
          x="1246"
          y="20"
          width="193"
          height="53"/>
      <archimateElement
          xsi:type="archimate:BusinessFunction"
          href="BusinessFunction_id-26682.xml#id-26682"/>
    </children>
    <children
        xsi:type="archimate:DiagramModelArchimateObject"
        id="id-38507"
        targetConnections="cbd40c45-29d0-4f44-82d3-1ff67e2c8865"
        font="1|Arial|10.0|0|WINDOWS|1|0|0|0|0|0|0|0|0|1|0|0|0|0|Arial"
        fontColor="#000000"
        lineColor="#000000"
        fillColor="#ffffcc">
      <bounds
          x="760"
          y="20"
          width="193"
          height="53"/>
      <archimateElement
          xsi:type="archimate:BusinessFunction"
          href="BusinessFunction_id-26694.xml#id-26694"/>
    </children>
    <children
        xsi:type="archimate:DiagramModelArchimateObject"
        id="id-38510"
        targetConnections="384096f4-10b2-4c40-b5e4-98fe28a27cad"
        font="1|Arial|10.0|0|WINDOWS|1|0|0|0|0|0|0|0|0|1|0|0|0|0|Arial"
        fontColor="#000000"
        lineColor="#000000"
        fillColor="#ffffcc">
      <bounds
          x="520"
          y="20"
          width="193"
          height="53"/>
      <archimateElement
          xsi:type="archimate:BusinessFunction"
          href="BusinessFunction_id-26700.xml#id-26700"/>
    </children>
    <children
        xsi:type="archimate:DiagramModelArchimateObject"
        id="id-38514"
        targetConnections="6da655bc-5e56-44f0-a0ce-962c8a7bb470"
        font="1|Arial|10.0|0|WINDOWS|1|0|0|0|0|0|0|0|0|1|0|0|0|0|Arial"
        fontColor="#000000"
        lineColor="#000000"
        fillColor="#ffffcc">
      <bounds
          x="33"
          y="20"
          width="193"
          height="53"/>
      <archimateElement
          xsi:type="archimate:BusinessFunction"
          href="BusinessFunction_id-26706.xml#id-26706"/>
    </children>
    <archimateElement
        xsi:type="archimate:BusinessFunction"
        href="BusinessFunction_id-26676.xml#id-26676"/>
  </children>
  <children
      xsi:type="archimate:DiagramModelArchimateObject"
      id="id-38518"
      font="1|Arial|10.0|0|WINDOWS|1|0|0|0|0|0|0|0|0|1|0|0|0|0|Arial"
      fontColor="#000000"
      lineColor="#000000"
      fillColor="#fff29b">
    <sourceConnections
        xsi:type="archimate:DiagramModelArchimateConnection"
        id="0e0f9343-e8cf-47bb-8a26-edbc00a4723c"
        source="id-38518"
        target="id-38520">
      <archimateRelationship
          xsi:type="archimate:AggregationRelationship"
          href="AggregationRelationship_id-35170.xml#id-35170"/>
    </sourceConnections>
    <sourceConnections
        xsi:type="archimate:DiagramModelArchimateConnection"
        id="106ff99e-dbdf-4025-abde-6a6357879b72"
        source="id-38518"
        target="id-38523">
      <archimateRelationship
          xsi:type="archimate:AggregationRelationship"
          href="AggregationRelationship_id-42367.xml#id-42367"/>
    </sourceConnections>
    <sourceConnections
        xsi:type="archimate:DiagramModelArchimateConnection"
        id="6d4bb35d-5220-401e-906a-40dc11f292b7"
        source="id-38518"
        target="id-38525">
      <archimateRelationship
          xsi:type="archimate:AggregationRelationship"
          href="AggregationRelationship_id-42263.xml#id-42263"/>
    </sourceConnections>
    <sourceConnections
        xsi:type="archimate:DiagramModelArchimateConnection"
        id="47cc53f5-eaa8-433f-8d0d-1d98647f1eb1"
        source="id-38518"
        target="id-38530">
      <archimateRelationship
          xsi:type="archimate:AggregationRelationship"
          href="AggregationRelationship_id-42405.xml#id-42405"/>
    </sourceConnections>
    <sourceConnections
        xsi:type="archimate:DiagramModelArchimateConnection"
        id="547e992a-ebe7-407c-8a37-8b2531cd8658"
        source="id-38518"
        target="id-38534">
      <archimateRelationship
          xsi:type="archimate:AggregationRelationship"
          href="AggregationRelationship_id-42401.xml#id-42401"/>
    </sourceConnections>
    <sourceConnections
        xsi:type="archimate:DiagramModelArchimateConnection"
        id="fe50b0ac-5a7c-4796-961b-909b58bea762"
        source="id-38518"
        target="id-38538">
      <archimateRelationship
          xsi:type="archimate:AggregationRelationship"
          href="AggregationRelationship_id-42216.xml#id-42216"/>
    </sourceConnections>
    <bounds
        x="47"
        y="133"
        width="1480"
        height="87"/>
    <children
        xsi:type="archimate:DiagramModelArchimateObject"
        id="id-38520"
        targetConnections="id-38583 0e0f9343-e8cf-47bb-8a26-edbc00a4723c"
        font="1|Arial|10.0|0|WINDOWS|1|0|0|0|0|0|0|0|0|1|0|0|0|0|Arial"
        fontColor="#000000"
        lineColor="#000000"
        fillColor="#ffffcc">
      <bounds
          x="1246"
          y="20"
          width="193"
          height="53"/>
      <archimateElement
          xsi:type="archimate:BusinessFunction"
          href="BusinessFunction_id-26718.xml#id-26718"/>
    </children>
    <children
        xsi:type="archimate:DiagramModelArchimateObject"
        id="id-38523"
        targetConnections="id-38549 106ff99e-dbdf-4025-abde-6a6357879b72"
        font="1|Arial|10.0|0|WINDOWS|1|0|0|0|0|0|0|0|0|1|0|0|0|0|Arial"
        fontColor="#000000"
        lineColor="#000000"
        fillColor="#ffffcc">
      <bounds
          x="1006"
          y="20"
          width="193"
          height="53"/>
      <archimateElement
          xsi:type="archimate:BusinessFunction"
          href="BusinessFunction_id-26730.xml#id-26730"/>
    </children>
    <children
        xsi:type="archimate:DiagramModelArchimateObject"
        id="id-38525"
        targetConnections="id-38557 6d4bb35d-5220-401e-906a-40dc11f292b7"
        font="1|Arial|10.0|0|WINDOWS|1|0|0|0|0|0|0|0|0|1|0|0|0|0|Arial"
        fontColor="#000000"
        lineColor="#000000"
        fillColor="#ffffcc">
      <bounds
          x="760"
          y="20"
          width="193"
          height="53"/>
      <archimateElement
          xsi:type="archimate:BusinessFunction"
          href="BusinessFunction_id-26736.xml#id-26736"/>
    </children>
    <children
        xsi:type="archimate:DiagramModelArchimateObject"
        id="id-38530"
        targetConnections="id-38565 47cc53f5-eaa8-433f-8d0d-1d98647f1eb1"
        font="1|Arial|10.0|0|WINDOWS|1|0|0|0|0|0|0|0|0|1|0|0|0|0|Arial"
        fontColor="#000000"
        lineColor="#000000"
        fillColor="#ffffcc">
      <bounds
          x="520"
          y="20"
          width="193"
          height="53"/>
      <archimateElement
          xsi:type="archimate:BusinessFunction"
          href="BusinessFunction_id-26742.xml#id-26742"/>
    </children>
    <children
        xsi:type="archimate:DiagramModelArchimateObject"
        id="id-38534"
        targetConnections="id-38542 547e992a-ebe7-407c-8a37-8b2531cd8658"
        font="1|Arial|10.0|0|WINDOWS|1|0|0|0|0|0|0|0|0|1|0|0|0|0|Arial"
        fontColor="#000000"
        lineColor="#000000"
        fillColor="#ffffcc">
      <bounds
          x="273"
          y="20"
          width="193"
          height="53"/>
      <archimateElement
          xsi:type="archimate:BusinessFunction"
          href="BusinessFunction_id-26748.xml#id-26748"/>
    </children>
    <children
        xsi:type="archimate:DiagramModelArchimateObject"
        id="id-38538"
        targetConnections="id-38569 fe50b0ac-5a7c-4796-961b-909b58bea762"
        font="1|Arial|10.0|0|WINDOWS|1|0|0|0|0|0|0|0|0|1|0|0|0|0|Arial"
        fontColor="#000000"
        lineColor="#000000"
        fillColor="#ffffcc">
      <bounds
          x="33"
          y="20"
          width="193"
          height="53"/>
      <archimateElement
          xsi:type="archimate:BusinessFunction"
          href="BusinessFunction_id-26754.xml#id-26754"/>
    </children>
    <archimateElement
        xsi:type="archimate:BusinessFunction"
        href="BusinessFunction_id-26712.xml#id-26712"/>
  </children>
  <children
      xsi:type="archimate:DiagramModelArchimateObject"
      id="id-38544"
      targetConnections="id-38539"
      font="1|Arial|10.0|0|WINDOWS|1|0|0|0|0|0|0|0|0|1|0|0|0|0|Arial"
      fontColor="#000000"
      lineColor="#000000"
      fillColor="#fff29b">
    <sourceConnections
        xsi:type="archimate:DiagramModelArchimateConnection"
        id="833f7d79-5539-4383-a086-efd31d9e0ddd"
        source="id-38544"
        target="id-38548">
      <archimateRelationship
          xsi:type="archimate:AggregationRelationship"
          href="AggregationRelationship_id-37732.xml#id-37732"/>
    </sourceConnections>
    <sourceConnections
        xsi:type="archimate:DiagramModelArchimateConnection"
        id="e68cd722-67ca-4be6-9baf-be1f6375c86e"
        source="id-38544"
        target="id-38551">
      <archimateRelationship
          xsi:type="archimate:AggregationRelationship"
          href="AggregationRelationship_id-37728.xml#id-37728"/>
    </sourceConnections>
    <sourceConnections
        xsi:type="archimate:DiagramModelArchimateConnection"
        id="7789db59-5b76-4017-8f78-4a1e3ffa2c0b"
        source="id-38544"
        target="id-38556">
      <archimateRelationship
          xsi:type="archimate:AggregationRelationship"
          href="AggregationRelationship_id-37730.xml#id-37730"/>
    </sourceConnections>
    <sourceConnections
        xsi:type="archimate:DiagramModelArchimateConnection"
        id="ff7af13d-8a89-45c0-8123-d2b00e8c45fc"
        source="id-38544"
        target="id-38560">
      <archimateRelationship
          xsi:type="archimate:AggregationRelationship"
          href="AggregationRelationship_id-37724.xml#id-37724"/>
    </sourceConnections>
    <sourceConnections
        xsi:type="archimate:DiagramModelArchimateConnection"
        id="88f34012-1b98-48ea-ab8d-5d9d76e9cc11"
        source="id-38544"
        target="id-38564">
      <archimateRelationship
          xsi:type="archimate:AggregationRelationship"
          href="AggregationRelationship_id-37726.xml#id-37726"/>
    </sourceConnections>
    <sourceConnections
        xsi:type="archimate:DiagramModelArchimateConnection"
        id="c73ac968-a34b-4501-8513-4d770d8c090f"
        source="id-38544"
        target="id-38568">
      <archimateRelationship
          xsi:type="archimate:AggregationRelationship"
          href="AggregationRelationship_id-37716.xml#id-37716"/>
    </sourceConnections>
    <bounds
        x="47"
        y="227"
        width="1480"
        height="87"/>
    <children
        xsi:type="archimate:DiagramModelArchimateObject"
        id="id-38548"
        targetConnections="833f7d79-5539-4383-a086-efd31d9e0ddd"
        font="1|Arial|10.0|0|WINDOWS|1|0|0|0|0|0|0|0|0|1|0|0|0|0|Arial"
        fontColor="#000000"
        lineColor="#000000"
        fillColor="#ffffcc">
      <bounds
          x="1246"
          y="20"
          width="193"
          height="53"/>
      <archimateElement
          xsi:type="archimate:BusinessFunction"
          href="BusinessFunction_id-26594.xml#id-26594"/>
    </children>
    <children
        xsi:type="archimate:DiagramModelArchimateObject"
        id="id-38551"
        targetConnections="e68cd722-67ca-4be6-9baf-be1f6375c86e"
        font="1|Arial|10.0|0|WINDOWS|1|0|0|0|0|0|0|0|0|1|0|0|0|0|Arial"
        fontColor="#000000"
        lineColor="#000000"
        fillColor="#ffffcc">
      <bounds
          x="1006"
          y="20"
          width="193"
          height="53"/>
      <archimateElement
          xsi:type="archimate:BusinessFunction"
          href="BusinessFunction_id-26600.xml#id-26600"/>
    </children>
    <children
        xsi:type="archimate:DiagramModelArchimateObject"
        id="id-38556"
        targetConnections="7789db59-5b76-4017-8f78-4a1e3ffa2c0b"
        font="1|Arial|10.0|0|WINDOWS|1|0|0|0|0|0|0|0|0|1|0|0|0|0|Arial"
        fontColor="#000000"
        lineColor="#000000"
        fillColor="#ffffcc">
      <bounds
          x="760"
          y="20"
          width="193"
          height="53"/>
      <archimateElement
          xsi:type="archimate:BusinessFunction"
          href="BusinessFunction_id-26610.xml#id-26610"/>
    </children>
    <children
        xsi:type="archimate:DiagramModelArchimateObject"
        id="id-38560"
        targetConnections="ff7af13d-8a89-45c0-8123-d2b00e8c45fc"
        font="1|Arial|10.0|0|WINDOWS|1|0|0|0|0|0|0|0|0|1|0|0|0|0|Arial"
        fontColor="#000000"
        lineColor="#000000"
        fillColor="#ffffcc">
      <bounds
          x="520"
          y="20"
          width="193"
          height="53"/>
      <archimateElement
          xsi:type="archimate:BusinessFunction"
          href="BusinessFunction_id-26618.xml#id-26618"/>
    </children>
    <children
        xsi:type="archimate:DiagramModelArchimateObject"
        id="id-38564"
        targetConnections="88f34012-1b98-48ea-ab8d-5d9d76e9cc11"
        font="1|Arial|10.0|0|WINDOWS|1|0|0|0|0|0|0|0|0|1|0|0|0|0|Arial"
        fontColor="#000000"
        lineColor="#000000"
        fillColor="#ffffcc">
      <bounds
          x="273"
          y="20"
          width="193"
          height="53"/>
      <archimateElement
          xsi:type="archimate:BusinessFunction"
          href="BusinessFunction_id-26624.xml#id-26624"/>
    </children>
    <children
        xsi:type="archimate:DiagramModelArchimateObject"
        id="id-38568"
        targetConnections="c73ac968-a34b-4501-8513-4d770d8c090f"
        font="1|Arial|10.0|0|WINDOWS|1|0|0|0|0|0|0|0|0|1|0|0|0|0|Arial"
        fontColor="#000000"
        lineColor="#000000"
        fillColor="#ffffcc">
      <bounds
          x="33"
          y="20"
          width="193"
          height="53"/>
      <archimateElement
          xsi:type="archimate:BusinessFunction"
          href="BusinessFunction_id-26634.xml#id-26634"/>
    </children>
    <archimateElement
        xsi:type="archimate:BusinessFunction"
        href="BusinessFunction_id-26588.xml#id-26588"/>
  </children>
  <children
      xsi:type="archimate:DiagramModelArchimateObject"
      id="id-38574"
      targetConnections="id-38535"
      font="1|Arial|10.0|0|WINDOWS|1|0|0|0|0|0|0|0|0|1|0|0|0|0|Arial"
      fontColor="#000000"
      lineColor="#000000"
      fillColor="#fff29b">
    <sourceConnections
        xsi:type="archimate:DiagramModelArchimateConnection"
        id="668e4110-c206-48c8-8f4d-83511e8466e2"
        source="id-38574"
        target="id-38577">
      <archimateRelationship
          xsi:type="archimate:AggregationRelationship"
          href="AggregationRelationship_id-42242.xml#id-42242"/>
    </sourceConnections>
    <sourceConnections
        xsi:type="archimate:DiagramModelArchimateConnection"
        id="cbfa2f75-529d-4c81-a359-f51fae8de491"
        source="id-38574"
        target="id-38582">
      <archimateRelationship
          xsi:type="archimate:AggregationRelationship"
          href="AggregationRelationship_id-42264.xml#id-42264"/>
    </sourceConnections>
    <sourceConnections
        xsi:type="archimate:DiagramModelArchimateConnection"
        id="31b4b754-e86d-42e7-bc04-0f9002fd076d"
        source="id-38574"
        target="id-38586">
      <archimateRelationship
          xsi:type="archimate:AggregationRelationship"
          href="AggregationRelationship_id-42293.xml#id-42293"/>
    </sourceConnections>
    <sourceConnections
        xsi:type="archimate:DiagramModelArchimateConnection"
        id="e930f9f2-58aa-4b06-a1ae-4194be3152c9"
        source="id-38574"
        target="id-38588">
      <archimateRelationship
          xsi:type="archimate:AggregationRelationship"
          href="AggregationRelationship_id-42256.xml#id-42256"/>
    </sourceConnections>
    <bounds
        x="47"
        y="320"
        width="1480"
        height="87"/>
    <children
        xsi:type="archimate:DiagramModelArchimateObject"
        id="id-38577"
        targetConnections="668e4110-c206-48c8-8f4d-83511e8466e2"
        font="1|Arial|10.0|0|WINDOWS|1|0|0|0|0|0|0|0|0|1|0|0|0|0|Arial"
        fontColor="#000000"
        lineColor="#000000"
        fillColor="#ffffcc">
      <bounds
          x="1246"
          y="20"
          width="193"
          height="53"/>
      <archimateElement
          xsi:type="archimate:BusinessFunction"
          href="BusinessFunction_id-26648.xml#id-26648"/>
    </children>
    <children
        xsi:type="archimate:DiagramModelArchimateObject"
        id="id-38582"
        targetConnections="cbfa2f75-529d-4c81-a359-f51fae8de491"
        font="1|Arial|10.0|0|WINDOWS|1|0|0|0|0|0|0|0|0|1|0|0|0|0|Arial"
        fontColor="#000000"
        lineColor="#000000"
        fillColor="#ffffcc">
      <bounds
          x="760"
          y="20"
          width="193"
          height="53"/>
      <archimateElement
          xsi:type="archimate:BusinessFunction"
          href="BusinessFunction_id-26658.xml#id-26658"/>
    </children>
    <children
        xsi:type="archimate:DiagramModelArchimateObject"
        id="id-38586"
        targetConnections="31b4b754-e86d-42e7-bc04-0f9002fd076d"
        font="1|Arial|10.0|0|WINDOWS|1|0|0|0|0|0|0|0|0|1|0|0|0|0|Arial"
        fontColor="#000000"
        lineColor="#000000"
        fillColor="#ffffcc">
      <bounds
          x="520"
          y="20"
          width="193"
          height="53"/>
      <archimateElement
          xsi:type="archimate:BusinessFunction"
          href="BusinessFunction_id-26664.xml#id-26664"/>
    </children>
    <children
        xsi:type="archimate:DiagramModelArchimateObject"
        id="id-38588"
        targetConnections="e930f9f2-58aa-4b06-a1ae-4194be3152c9"
        font="1|Arial|10.0|0|WINDOWS|1|0|0|0|0|0|0|0|0|1|0|0|0|0|Arial"
        fontColor="#000000"
        lineColor="#000000"
        fillColor="#ffffcc">
      <bounds
          x="33"
          y="20"
          width="193"
          height="53"/>
      <archimateElement
          xsi:type="archimate:BusinessFunction"
          href="BusinessFunction_id-26670.xml#id-26670"/>
    </children>
    <archimateElement
        xsi:type="archimate:BusinessFunction"
        href="BusinessFunction_id-26644.xml#id-26644"/>
  </children>
  <children
      xsi:type="archimate:DiagramModelArchimateObject"
      id="id-38590"
      targetConnections="id-38531"
      font="1|Arial|10.0|0|WINDOWS|1|0|0|0|0|0|0|0|0|1|0|0|0|0|Arial"
      fontColor="#000000"
      lineColor="#000000"
      fillColor="#fff29b">
    <sourceConnections
        xsi:type="archimate:DiagramModelArchimateConnection"
        id="2a4a3117-999a-4105-95df-afcbcc0b3865"
        source="id-38590"
        target="id-38591">
      <archimateRelationship
          xsi:type="archimate:AggregationRelationship"
          href="AggregationRelationship_id-42176.xml#id-42176"/>
    </sourceConnections>
    <sourceConnections
        xsi:type="archimate:DiagramModelArchimateConnection"
        id="d42739c2-3d66-4c88-aa9a-ee3ad1f09109"
        source="id-38590"
        target="id-38593">
      <archimateRelationship
          xsi:type="archimate:AggregationRelationship"
          href="AggregationRelationship_id-42187.xml#id-42187"/>
    </sourceConnections>
    <sourceConnections
        xsi:type="archimate:DiagramModelArchimateConnection"
        id="b003cdb3-e271-4964-a13d-a2d3bedcab99"
        source="id-38590"
        target="id-38595">
      <archimateRelationship
          xsi:type="archimate:AggregationRelationship"
          href="AggregationRelationship_id-42181.xml#id-42181"/>
    </sourceConnections>
    <sourceConnections
        xsi:type="archimate:DiagramModelArchimateConnection"
        id="3175a8ef-3928-437e-ade2-f1a770771b00"
        source="id-38590"
        target="id-38598">
      <archimateRelationship
          xsi:type="archimate:AggregationRelationship"
          href="AggregationRelationship_id-42168.xml#id-42168"/>
    </sourceConnections>
    <sourceConnections
        xsi:type="archimate:DiagramModelArchimateConnection"
        id="2925a95f-afaf-4a9e-8cf6-effeb246180b"
        source="id-38590"
        target="id-38601">
      <archimateRelationship
          xsi:type="archimate:AggregationRelationship"
          href="AggregationRelationship_id-31700.xml#id-31700"/>
    </sourceConnections>
    <sourceConnections
        xsi:type="archimate:DiagramModelArchimateConnection"
        id="53736645-193b-4d64-aa08-afb0a187679a"
        source="id-38590"
        target="id-38495">
      <archimateRelationship
          xsi:type="archimate:AggregationRelationship"
          href="AggregationRelationship_id-26893.xml#id-26893"/>
    </sourceConnections>
    <sourceConnections
        xsi:type="archimate:DiagramModelArchimateConnection"
        id="7b6a9e2c-d757-40a8-8175-f54cb0d756fd"
        source="id-38590"
        target="id-38498">
      <archimateRelationship
          xsi:type="archimate:AggregationRelationship"
          href="AggregationRelationship_id-42175.xml#id-42175"/>
    </sourceConnections>
    <sourceConnections
        xsi:type="archimate:DiagramModelArchimateConnection"
        id="ac983ed9-2889-4b1b-a782-af8578bfae03"
        source="id-38590"
        target="id-38501">
      <archimateRelationship
          xsi:type="archimate:AggregationRelationship"
          href="AggregationRelationship_id-26849.xml#id-26849"/>
    </sourceConnections>
    <bounds
        x="47"
        y="413"
        width="1480"
        height="153"/>
    <children
        xsi:type="archimate:DiagramModelArchimateObject"
        id="id-38591"
        targetConnections="2a4a3117-999a-4105-95df-afcbcc0b3865"
        font="1|Arial|10.0|0|WINDOWS|1|0|0|0|0|0|0|0|0|1|0|0|0|0|Arial"
        fontColor="#000000"
        lineColor="#000000"
        fillColor="#ffffcc">
      <bounds
          x="520"
          y="20"
          width="193"
          height="53"/>
      <archimateElement
          xsi:type="archimate:BusinessFunction"
          href="BusinessFunction_id-26766.xml#id-26766"/>
    </children>
    <children
        xsi:type="archimate:DiagramModelArchimateObject"
        id="id-38593"
        targetConnections="d42739c2-3d66-4c88-aa9a-ee3ad1f09109"
        font="1|Arial|10.0|0|WINDOWS|1|0|0|0|0|0|0|0|0|1|0|0|0|0|Arial"
        fontColor="#000000"
        lineColor="#000000"
        fillColor="#ffffcc">
      <bounds
          x="1246"
          y="80"
          width="193"
          height="53"/>
      <archimateElement
          xsi:type="archimate:BusinessFunction"
          href="BusinessFunction_id-26772.xml#id-26772"/>
    </children>
    <children
        xsi:type="archimate:DiagramModelArchimateObject"
        id="id-38595"
        targetConnections="b003cdb3-e271-4964-a13d-a2d3bedcab99"
        font="1|Arial|10.0|0|WINDOWS|1|0|0|0|0|0|0|0|0|1|0|0|0|0|Arial"
        fontColor="#000000"
        lineColor="#000000"
        fillColor="#ffffcc">
      <bounds
          x="1246"
          y="20"
          width="193"
          height="53"/>
      <archimateElement
          xsi:type="archimate:BusinessFunction"
          href="BusinessFunction_id-26778.xml#id-26778"/>
    </children>
    <children
        xsi:type="archimate:DiagramModelArchimateObject"
        id="id-38598"
        targetConnections="3175a8ef-3928-437e-ade2-f1a770771b00"
        font="1|Arial|10.0|0|WINDOWS|1|0|0|0|0|0|0|0|0|1|0|0|0|0|Arial"
        fontColor="#000000"
        lineColor="#000000"
        fillColor="#ffffcc">
      <bounds
          x="33"
          y="20"
          width="193"
          height="53"/>
      <archimateElement
          xsi:type="archimate:BusinessFunction"
          href="BusinessFunction_id-26784.xml#id-26784"/>
    </children>
    <children
        xsi:type="archimate:DiagramModelArchimateObject"
        id="id-38601"
        targetConnections="2925a95f-afaf-4a9e-8cf6-effeb246180b"
        font="1|Arial|10.0|0|WINDOWS|1|0|0|0|0|0|0|0|0|1|0|0|0|0|Arial"
        fontColor="#000000"
        lineColor="#000000"
        fillColor="#ffffcc">
      <bounds
          x="520"
          y="87"
          width="193"
          height="53"/>
      <archimateElement
          xsi:type="archimate:BusinessFunction"
          href="BusinessFunction_id-26790.xml#id-26790"/>
    </children>
    <children
        xsi:type="archimate:DiagramModelArchimateObject"
        id="id-38495"
        targetConnections="53736645-193b-4d64-aa08-afb0a187679a"
        font="1|Arial|10.0|0|WINDOWS|1|0|0|0|0|0|0|0|0|1|0|0|0|0|Arial"
        fontColor="#000000"
        lineColor="#000000"
        fillColor="#ffffcc">
      <bounds
          x="760"
          y="87"
          width="193"
          height="53"/>
      <archimateElement
          xsi:type="archimate:BusinessFunction"
          href="BusinessFunction_id-26586.xml#id-26586"/>
    </children>
    <children
        xsi:type="archimate:DiagramModelArchimateObject"
        id="id-38498"
        targetConnections="7b6a9e2c-d757-40a8-8175-f54cb0d756fd"
        font="1|Arial|10.0|0|WINDOWS|1|0|0|0|0|0|0|0|0|1|0|0|0|0|Arial"
        fontColor="#000000"
        lineColor="#000000"
        fillColor="#ffffcc">
      <bounds
          x="33"
          y="87"
          width="193"
          height="53"/>
      <archimateElement
          xsi:type="archimate:BusinessFunction"
          href="BusinessFunction_id-26596.xml#id-26596"/>
    </children>
    <children
        xsi:type="archimate:DiagramModelArchimateObject"
        id="id-38501"
        targetConnections="ac983ed9-2889-4b1b-a782-af8578bfae03"
        font="1|Arial|10.0|0|WINDOWS|1|0|0|0|0|0|0|0|0|1|0|0|0|0|Arial"
        fontColor="#000000"
        lineColor="#000000"
        fillColor="#ffffcc">
      <bounds
          x="760"
          y="20"
          width="193"
          height="53"/>
      <archimateElement
          xsi:type="archimate:BusinessFunction"
          href="BusinessFunction_id-26604.xml#id-26604"/>
    </children>
    <archimateElement
        xsi:type="archimate:BusinessFunction"
        href="BusinessFunction_id-26760.xml#id-26760"/>
  </children>
  <children
      xsi:type="archimate:DiagramModelArchimateObject"
      id="id-38506"
      font="1|Arial|10.0|0|WINDOWS|1|0|0|0|0|0|0|0|0|1|0|0|0|0|Arial"
      fontColor="#000000"
      lineColor="#000000"
      fillColor="#fff29b">
    <sourceConnections
        xsi:type="archimate:DiagramModelArchimateConnection"
        id="a154ae3b-5b0b-4614-a88a-a49e7f5a8862"
        source="id-38506"
        target="id-38508">
      <archimateRelationship
          xsi:type="archimate:AggregationRelationship"
          href="AggregationRelationship_id-42358.xml#id-42358"/>
    </sourceConnections>
    <sourceConnections
        xsi:type="archimate:DiagramModelArchimateConnection"
        id="8f300166-5623-4824-899c-a9ddf1297ced"
        source="id-38506"
        target="id-38511">
      <archimateRelationship
          xsi:type="archimate:AggregationRelationship"
          href="AggregationRelationship_id-42239.xml#id-42239"/>
    </sourceConnections>
    <sourceConnections
        xsi:type="archimate:DiagramModelArchimateConnection"
        id="bc2b4641-4d93-4913-9440-2252af698a3f"
        source="id-38506"
        target="id-38526">
      <archimateRelationship
          xsi:type="archimate:AggregationRelationship"
          href="AggregationRelationship_id-42232.xml#id-42232"/>
    </sourceConnections>
    <sourceConnections
        xsi:type="archimate:DiagramModelArchimateConnection"
        id="dc56b210-92c7-4896-925c-7604d3e69756"
        source="id-38506"
        target="id-38552">
      <archimateRelationship
          xsi:type="archimate:AggregationRelationship"
          href="AggregationRelationship_id-42231.xml#id-42231"/>
    </sourceConnections>
    <sourceConnections
        xsi:type="archimate:DiagramModelArchimateConnection"
        id="7063d048-27ba-483f-9e63-39ce94086fcf"
        source="id-38506"
        target="id-38578">
      <archimateRelationship
          xsi:type="archimate:AggregationRelationship"
          href="AggregationRelationship_id-42238.xml#id-42238"/>
    </sourceConnections>
    <bounds
        x="47"
        y="580"
        width="1480"
        height="387"/>
    <children
        xsi:type="archimate:DiagramModelArchimateObject"
        id="id-38508"
        targetConnections="id-38527 a154ae3b-5b0b-4614-a88a-a49e7f5a8862"
        font="1|Arial|10.0|0|WINDOWS|1|0|0|0|0|0|0|0|0|1|0|0|0|0|Arial"
        fontColor="#000000"
        lineColor="#000000"
        fillColor="#fff8b7">
      <bounds
          x="13"
          y="320"
          width="1447"
          height="47"/>
      <archimateElement
          xsi:type="archimate:BusinessFunction"
          href="BusinessFunction_id-26620.xml#id-26620"/>
    </children>
    <children
        xsi:type="archimate:DiagramModelArchimateObject"
        id="id-38511"
        targetConnections="id-38553 8f300166-5623-4824-899c-a9ddf1297ced"
        font="1|Arial|10.0|0|WINDOWS|1|0|0|0|0|0|0|0|0|1|0|0|0|0|Arial"
        fontColor="#000000"
        lineColor="#000000"
        fillColor="#fff8b7">
      <sourceConnections
          xsi:type="archimate:DiagramModelArchimateConnection"
          id="70d3a2f6-7323-4404-be3d-7680e6f88791"
          source="id-38511"
          target="id-38513">
        <archimateRelationship
            xsi:type="archimate:AggregationRelationship"
            href="AggregationRelationship_id-42250.xml#id-42250"/>
      </sourceConnections>
      <sourceConnections
          xsi:type="archimate:DiagramModelArchimateConnection"
          id="9d784b7c-a4fc-4df9-802b-0c2df0571910"
          source="id-38511"
          target="id-38516">
        <archimateRelationship
            xsi:type="archimate:AggregationRelationship"
            href="AggregationRelationship_id-42244.xml#id-42244"/>
      </sourceConnections>
      <sourceConnections
          xsi:type="archimate:DiagramModelArchimateConnection"
          id="897eca70-85c6-4c8e-9dd6-3597681e08c1"
          source="id-38511"
          target="id-38519">
        <archimateRelationship
            xsi:type="archimate:AggregationRelationship"
            href="AggregationRelationship_id-32642.xml#id-32642"/>
      </sourceConnections>
      <sourceConnections
          xsi:type="archimate:DiagramModelArchimateConnection"
          id="0812cb17-9e3f-455f-ab79-f5221204650f"
          source="id-38511"
          target="id-38522">
        <archimateRelationship
            xsi:type="archimate:AggregationRelationship"
            href="AggregationRelationship_id-42273.xml#id-42273"/>
      </sourceConnections>
      <bounds
          x="13"
          y="27"
          width="347"
          height="280"/>
      <children
          xsi:type="archimate:DiagramModelArchimateObject"
          id="id-38513"
          targetConnections="70d3a2f6-7323-4404-be3d-7680e6f88791"
          font="1|Arial|10.0|0|WINDOWS|1|0|0|0|0|0|0|0|0|1|0|0|0|0|Arial"
          fontColor="#000000"
          lineColor="#000000"
          fillColor="#ffffcc">
        <bounds
            x="180"
            y="86"
            width="147"
            height="53"/>
        <archimateElement
            xsi:type="archimate:BusinessFunction"
            href="BusinessFunction_id-27712.xml#id-27712"/>
      </children>
      <children
          xsi:type="archimate:DiagramModelArchimateObject"
          id="id-38516"
          targetConnections="9d784b7c-a4fc-4df9-802b-0c2df0571910"
          font="1|Arial|10.0|0|WINDOWS|1|0|0|0|0|0|0|0|0|1|0|0|0|0|Arial"
          fontColor="#000000"
          lineColor="#000000"
          fillColor="#ffffcc">
        <bounds
            x="180"
            y="26"
            width="147"
            height="53"/>
        <archimateElement
            xsi:type="archimate:BusinessFunction"
            href="BusinessFunction_id-28046.xml#id-28046"/>
      </children>
      <children
          xsi:type="archimate:DiagramModelArchimateObject"
          id="id-38519"
          targetConnections="897eca70-85c6-4c8e-9dd6-3597681e08c1"
          font="1|Arial|10.0|0|WINDOWS|1|0|0|0|0|0|0|0|0|1|0|0|0|0|Arial"
          fontColor="#000000"
          lineColor="#000000"
          fillColor="#ffffcc">
        <bounds
            x="13"
            y="86"
            width="147"
            height="53"/>
        <archimateElement
            xsi:type="archimate:BusinessFunction"
            href="BusinessFunction_id-27835.xml#id-27835"/>
      </children>
      <children
          xsi:type="archimate:DiagramModelArchimateObject"
          id="id-38522"
          targetConnections="0812cb17-9e3f-455f-ab79-f5221204650f"
          font="1|Arial|10.0|0|WINDOWS|1|0|0|0|0|0|0|0|0|1|0|0|0|0|Arial"
          fontColor="#000000"
          lineColor="#000000"
          fillColor="#ffffcc">
        <bounds
            x="20"
            y="26"
            width="147"
            height="53"/>
        <archimateElement
            xsi:type="archimate:BusinessFunction"
            href="BusinessFunction_id-26851.xml#id-26851"/>
      </children>
      <archimateElement
          xsi:type="archimate:BusinessFunction"
          href="BusinessFunction_id-26628.xml#id-26628"/>
    </children>
    <children
        xsi:type="archimate:DiagramModelArchimateObject"
        id="id-38526"
        targetConnections="id-38546 bc2b4641-4d93-4913-9440-2252af698a3f"
        font="1|Arial|10.0|0|WINDOWS|1|0|0|0|0|0|0|0|0|1|0|0|0|0|Arial"
        fontColor="#000000"
        lineColor="#000000"
        fillColor="#fff8b7">
      <sourceConnections
          xsi:type="archimate:DiagramModelArchimateConnection"
          id="4708455c-6665-4752-a6f0-b5346045674f"
          source="id-38526"
          target="id-38529">
        <archimateRelationship
            xsi:type="archimate:AggregationRelationship"
            href="AggregationRelationship_id-29970.xml#id-29970"/>
      </sourceConnections>
      <sourceConnections
          xsi:type="archimate:DiagramModelArchimateConnection"
          id="2713ae67-7d37-4c0f-9ade-10eb6a58532b"
          source="id-38526"
          target="id-38533">
        <archimateRelationship
            xsi:type="archimate:AggregationRelationship"
            href="AggregationRelationship_id-29966.xml#id-29966"/>
      </sourceConnections>
      <sourceConnections
          xsi:type="archimate:DiagramModelArchimateConnection"
          id="dd31844c-0841-4a2f-84d5-ce7d9a25f67c"
          source="id-38526"
          target="id-38537">
        <archimateRelationship
            xsi:type="archimate:AggregationRelationship"
            href="AggregationRelationship_id-30430.xml#id-30430"/>
      </sourceConnections>
      <sourceConnections
          xsi:type="archimate:DiagramModelArchimateConnection"
          id="7163fab3-2cf7-4d06-9eac-2a5698f4acfa"
          source="id-38526"
          target="id-38541">
        <archimateRelationship
            xsi:type="archimate:AggregationRelationship"
            href="AggregationRelationship_id-42389.xml#id-42389"/>
      </sourceConnections>
      <sourceConnections
          xsi:type="archimate:DiagramModelArchimateConnection"
          id="7425c071-f33f-452f-8a41-24be0e8fd1f3"
          source="id-38526"
          target="id-38545">
        <archimateRelationship
            xsi:type="archimate:AggregationRelationship"
            href="AggregationRelationship_id-40959.xml#id-40959"/>
      </sourceConnections>
      <bounds
          x="380"
          y="27"
          width="347"
          height="280"/>
      <children
          xsi:type="archimate:DiagramModelArchimateObject"
          id="id-38529"
          targetConnections="4708455c-6665-4752-a6f0-b5346045674f"
          font="1|Arial|10.0|0|WINDOWS|1|0|0|0|0|0|0|0|0|1|0|0|0|0|Arial"
          fontColor="#000000"
          lineColor="#000000"
          fillColor="#ffffcc">
        <bounds
            x="13"
            y="86"
            width="147"
            height="53"/>
        <archimateElement
            xsi:type="archimate:BusinessFunction"
            href="BusinessFunction_id-28490.xml#id-28490"/>
      </children>
      <children
          xsi:type="archimate:DiagramModelArchimateObject"
          id="id-38533"
          targetConnections="2713ae67-7d37-4c0f-9ade-10eb6a58532b"
          font="1|Arial|10.0|0|WINDOWS|1|0|0|0|0|0|0|0|0|1|0|0|0|0|Arial"
          fontColor="#000000"
          lineColor="#000000"
          fillColor="#ffffcc">
        <bounds
            x="13"
            y="146"
            width="147"
            height="53"/>
        <archimateElement
            xsi:type="archimate:BusinessFunction"
            href="BusinessFunction_id-27873.xml#id-27873"/>
      </children>
      <children
          xsi:type="archimate:DiagramModelArchimateObject"
          id="id-38537"
          targetConnections="dd31844c-0841-4a2f-84d5-ce7d9a25f67c"
          font="1|Arial|10.0|0|WINDOWS|1|0|0|0|0|0|0|0|0|1|0|0|0|0|Arial"
          fontColor="#000000"
          lineColor="#000000"
          fillColor="#ffffcc">
        <bounds
            x="13"
            y="26"
            width="147"
            height="53"/>
        <archimateElement
            xsi:type="archimate:BusinessFunction"
            href="BusinessFunction_id-28355.xml#id-28355"/>
      </children>
      <children
          xsi:type="archimate:DiagramModelArchimateObject"
          id="id-38541"
          targetConnections="7163fab3-2cf7-4d06-9eac-2a5698f4acfa"
          font="1|Arial|10.0|0|WINDOWS|1|0|0|0|0|0|0|0|0|1|0|0|0|0|Arial"
          fontColor="#000000"
          lineColor="#000000"
          fillColor="#ffffcc">
        <bounds
            x="173"
            y="146"
            width="147"
            height="53"/>
        <archimateElement
            xsi:type="archimate:BusinessFunction"
            href="BusinessFunction_id-28132.xml#id-28132"/>
      </children>
      <children
          xsi:type="archimate:DiagramModelArchimateObject"
          id="id-38545"
          targetConnections="7425c071-f33f-452f-8a41-24be0e8fd1f3"
          font="1|Arial|10.0|0|WINDOWS|1|0|0|0|0|0|0|0|0|1|0|0|0|0|Arial"
          fontColor="#000000"
          lineColor="#000000"
          fillColor="#ffffcc">
        <bounds
            x="173"
            y="26"
            width="147"
            height="53"/>
        <archimateElement
            xsi:type="archimate:BusinessFunction"
            href="BusinessFunction_id-28408.xml#id-28408"/>
      </children>
      <archimateElement
          xsi:type="archimate:BusinessFunction"
          href="BusinessFunction_id-26636.xml#id-26636"/>
    </children>
    <children
        xsi:type="archimate:DiagramModelArchimateObject"
        id="id-38552"
        targetConnections="id-38572 dc56b210-92c7-4896-925c-7604d3e69756"
        font="1|Arial|10.0|0|WINDOWS|1|0|0|0|0|0|0|0|0|1|0|0|0|0|Arial"
        fontColor="#000000"
        lineColor="#000000"
        fillColor="#fff8b7">
      <sourceConnections
          xsi:type="archimate:DiagramModelArchimateConnection"
          id="cfb39d84-8d0d-4595-bb20-8e3e9ab6a905"
          source="id-38552"
          target="id-38555">
        <archimateRelationship
            xsi:type="archimate:AggregationRelationship"
            href="AggregationRelationship_id-42400.xml#id-42400"/>
      </sourceConnections>
      <sourceConnections
          xsi:type="archimate:DiagramModelArchimateConnection"
          id="28f01437-4053-470d-849d-dc88df0efc57"
          source="id-38552"
          target="id-38559">
        <archimateRelationship
            xsi:type="archimate:AggregationRelationship"
            href="AggregationRelationship_id-42424.xml#id-42424"/>
      </sourceConnections>
      <sourceConnections
          xsi:type="archimate:DiagramModelArchimateConnection"
          id="0897c120-50dd-4c47-b778-84393a25d242"
          source="id-38552"
          target="id-38563">
        <archimateRelationship
            xsi:type="archimate:AggregationRelationship"
            href="AggregationRelationship_id-30017.xml#id-30017"/>
      </sourceConnections>
      <sourceConnections
          xsi:type="archimate:DiagramModelArchimateConnection"
          id="1802091a-1e23-4086-977f-1d735bc9ae74"
          source="id-38552"
          target="id-38567">
        <archimateRelationship
            xsi:type="archimate:AggregationRelationship"
            href="AggregationRelationship_id-30015.xml#id-30015"/>
      </sourceConnections>
      <sourceConnections
          xsi:type="archimate:DiagramModelArchimateConnection"
          id="2ce33f20-5316-4675-a0b2-90627ac9bf42"
          source="id-38552"
          target="id-38571">
        <archimateRelationship
            xsi:type="archimate:AggregationRelationship"
            href="AggregationRelationship_id-42364.xml#id-42364"/>
      </sourceConnections>
      <bounds
          x="1113"
          y="27"
          width="347"
          height="280"/>
      <children
          xsi:type="archimate:DiagramModelArchimateObject"
          id="id-38555"
          targetConnections="cfb39d84-8d0d-4595-bb20-8e3e9ab6a905"
          font="1|Arial|10.0|0|WINDOWS|1|0|0|0|0|0|0|0|0|1|0|0|0|0|Arial"
          fontColor="#000000"
          lineColor="#000000"
          fillColor="#ffffcc">
        <bounds
            x="180"
            y="26"
            width="147"
            height="53"/>
        <archimateElement
            xsi:type="archimate:BusinessFunction"
            href="BusinessFunction_id-26973.xml#id-26973"/>
      </children>
      <children
          xsi:type="archimate:DiagramModelArchimateObject"
          id="id-38559"
          targetConnections="28f01437-4053-470d-849d-dc88df0efc57"
          font="1|Arial|10.0|0|WINDOWS|1|0|0|0|0|0|0|0|0|1|0|0|0|0|Arial"
          fontColor="#000000"
          lineColor="#000000"
          fillColor="#ffffcc">
        <bounds
            x="20"
            y="26"
            width="147"
            height="53"/>
        <archimateElement
            xsi:type="archimate:BusinessFunction"
            href="BusinessFunction_id-27660.xml#id-27660"/>
      </children>
      <children
          xsi:type="archimate:DiagramModelArchimateObject"
          id="id-38563"
          targetConnections="0897c120-50dd-4c47-b778-84393a25d242"
          font="1|Arial|10.0|0|WINDOWS|1|0|0|0|0|0|0|0|0|1|0|0|0|0|Arial"
          fontColor="#000000"
          lineColor="#000000"
          fillColor="#ffffcc">
        <bounds
            x="20"
            y="86"
            width="147"
            height="53"/>
        <archimateElement
            xsi:type="archimate:BusinessFunction"
            href="BusinessFunction_id-27691.xml#id-27691"/>
      </children>
      <children
          xsi:type="archimate:DiagramModelArchimateObject"
          id="id-38567"
          targetConnections="1802091a-1e23-4086-977f-1d735bc9ae74"
          font="1|Arial|10.0|0|WINDOWS|1|0|0|0|0|0|0|0|0|1|0|0|0|0|Arial"
          fontColor="#000000"
          lineColor="#000000"
          fillColor="#ffffcc">
        <bounds
            x="20"
            y="146"
            width="147"
            height="53"/>
        <archimateElement
            xsi:type="archimate:BusinessFunction"
            href="BusinessFunction_id-28077.xml#id-28077"/>
      </children>
      <children
          xsi:type="archimate:DiagramModelArchimateObject"
          id="id-38571"
          targetConnections="2ce33f20-5316-4675-a0b2-90627ac9bf42"
          font="1|Arial|10.0|0|WINDOWS|1|0|0|0|0|0|0|0|0|1|0|0|0|0|Arial"
          fontColor="#000000"
          lineColor="#000000"
          fillColor="#ffffcc">
        <bounds
            x="180"
            y="86"
            width="147"
            height="53"/>
        <archimateElement
            xsi:type="archimate:BusinessFunction"
            href="BusinessFunction_id-27871.xml#id-27871"/>
      </children>
      <archimateElement
          xsi:type="archimate:BusinessFunction"
          href="BusinessFunction_id-26642.xml#id-26642"/>
    </children>
    <children
        xsi:type="archimate:DiagramModelArchimateObject"
        id="id-38578"
        targetConnections="id-38561 7063d048-27ba-483f-9e63-39ce94086fcf"
        font="1|Arial|10.0|0|WINDOWS|1|0|0|0|0|0|0|0|0|1|0|0|0|0|Arial"
        fontColor="#000000"
        lineColor="#000000"
        fillColor="#fff8b7">
      <sourceConnections
          xsi:type="archimate:DiagramModelArchimateConnection"
          id="3cba1218-f3ec-4db6-ae57-b980bb2410a6"
          source="id-38578"
          target="id-38579">
        <archimateRelationship
            xsi:type="archimate:AggregationRelationship"
            href="AggregationRelationship_id-42410.xml#id-42410"/>
      </sourceConnections>
      <sourceConnections
          xsi:type="archimate:DiagramModelArchimateConnection"
          id="c319f4cc-7ae3-411b-b9f8-d89cc8800abe"
          source="id-38578"
          target="id-38585">
        <archimateRelationship
            xsi:type="archimate:AggregationRelationship"
            href="AggregationRelationship_id-30020.xml#id-30020"/>
      </sourceConnections>
      <sourceConnections
          xsi:type="archimate:DiagramModelArchimateConnection"
          id="f1179d5d-9cd2-4a54-8930-213dce571520"
          source="id-38578"
          target="id-38587">
        <archimateRelationship
            xsi:type="archimate:AggregationRelationship"
            href="AggregationRelationship_id-32647.xml#id-32647"/>
      </sourceConnections>
      <sourceConnections
          xsi:type="archimate:DiagramModelArchimateConnection"
          id="1cdbdde6-3392-4e65-885b-0aed53d9db47"
          source="id-38578"
          target="id-38589">
        <archimateRelationship
            xsi:type="archimate:AggregationRelationship"
            href="AggregationRelationship_id-31725.xml#id-31725"/>
      </sourceConnections>
      <bounds
          x="746"
          y="27"
          width="347"
          height="280"/>
      <children
          xsi:type="archimate:DiagramModelArchimateObject"
          id="id-38579"
          targetConnections="3cba1218-f3ec-4db6-ae57-b980bb2410a6"
          font="1|Arial|10.0|0|WINDOWS|1|0|0|0|0|0|0|0|0|1|0|0|0|0|Arial"
          fontColor="#000000"
          lineColor="#000000"
          fillColor="#ffffcc">
        <bounds
            x="180"
            y="86"
            width="147"
            height="53"/>
        <archimateElement
            xsi:type="archimate:BusinessFunction"
            href="BusinessFunction_id-28406.xml#id-28406"/>
      </children>
      <children
          xsi:type="archimate:DiagramModelArchimateObject"
          id="id-38585"
          targetConnections="c319f4cc-7ae3-411b-b9f8-d89cc8800abe"
          font="1|Arial|10.0|0|WINDOWS|1|0|0|0|0|0|0|0|0|1|0|0|0|0|Arial"
          fontColor="#000000"
          lineColor="#000000"
          fillColor="#ffffcc">
        <bounds
            x="20"
            y="26"
            width="147"
            height="53"/>
        <archimateElement
            xsi:type="archimate:BusinessFunction"
            href="BusinessFunction_id-28539.xml#id-28539"/>
      </children>
      <children
          xsi:type="archimate:DiagramModelArchimateObject"
          id="id-38587"
          targetConnections="f1179d5d-9cd2-4a54-8930-213dce571520"
          font="1|Arial|10.0|0|WINDOWS|1|0|0|0|0|0|0|0|0|1|0|0|0|0|Arial"
          fontColor="#000000"
          lineColor="#000000"
          fillColor="#ffffcc">
        <bounds
            x="20"
            y="86"
            width="147"
            height="53"/>
        <archimateElement
            xsi:type="archimate:BusinessFunction"
            href="BusinessFunction_id-28020.xml#id-28020"/>
      </children>
      <children
          xsi:type="archimate:DiagramModelArchimateObject"
          id="id-38589"
          targetConnections="1cdbdde6-3392-4e65-885b-0aed53d9db47"
          font="1|Arial|10.0|0|WINDOWS|1|0|0|0|0|0|0|0|0|1|0|0|0|0|Arial"
          fontColor="#000000"
          lineColor="#000000"
          fillColor="#ffffcc">
        <bounds
            x="180"
            y="26"
            width="147"
            height="53"/>
        <archimateElement
            xsi:type="archimate:BusinessFunction"
            href="BusinessFunction_id-28105.xml#id-28105"/>
      </children>
      <archimateElement
          xsi:type="archimate:BusinessFunction"
          href="BusinessFunction_id-26652.xml#id-26652"/>
    </children>
    <archimateElement
        xsi:type="archimate:BusinessFunction"
        href="BusinessFunction_id-26612.xml#id-26612"/>
  </children>
  <children
      xsi:type="archimate:DiagramModelArchimateObject"
      id="id-38592"
      targetConnections="id-38580"
      font="1|Arial|10.0|0|WINDOWS|1|0|0|0|0|0|0|0|0|1|0|0|0|0|Arial"
      fontColor="#000000"
      lineColor="#000000"
      fillColor="#fff29b">
    <sourceConnections
        xsi:type="archimate:DiagramModelArchimateConnection"
        id="abcbd556-06fa-479a-abba-fec02413e493"
        source="id-38592"
        target="id-38594">
      <archimateRelationship
          xsi:type="archimate:AggregationRelationship"
          href="AggregationRelationship_id-40993.xml#id-40993"/>
    </sourceConnections>
    <sourceConnections
        xsi:type="archimate:DiagramModelArchimateConnection"
        id="884e6e60-adc7-42bc-b729-4abba1a6f188"
        source="id-38592"
        target="id-38596">
      <archimateRelationship
          xsi:type="archimate:AggregationRelationship"
          href="AggregationRelationship_id-41032.xml#id-41032"/>
    </sourceConnections>
    <sourceConnections
        xsi:type="archimate:DiagramModelArchimateConnection"
        id="f04b8064-2070-4cd0-89d7-0472854d3b22"
        source="id-38592"
        target="id-38599">
      <archimateRelationship
          xsi:type="archimate:AggregationRelationship"
          href="AggregationRelationship_id-41039.xml#id-41039"/>
    </sourceConnections>
    <sourceConnections
        xsi:type="archimate:DiagramModelArchimateConnection"
        id="4a942697-4501-4042-b1a9-efe885f5bf84"
        source="id-38592"
        target="id-38602">
      <archimateRelationship
          xsi:type="archimate:AggregationRelationship"
          href="AggregationRelationship_id-40986.xml#id-40986"/>
    </sourceConnections>
    <sourceConnections
        xsi:type="archimate:DiagramModelArchimateConnection"
        id="7357fa85-11de-4112-9d36-053353d55c30"
        source="id-38592"
        target="id-38496">
      <archimateRelationship
          xsi:type="archimate:AggregationRelationship"
          href="AggregationRelationship_id-28690.xml#id-28690"/>
    </sourceConnections>
    <sourceConnections
        xsi:type="archimate:DiagramModelArchimateConnection"
        id="0b0adccc-1a7a-4da5-99b4-c17bdd447d0e"
        source="id-38592"
        target="id-38499">
      <archimateRelationship
          xsi:type="archimate:AggregationRelationship"
          href="AggregationRelationship_id-41019.xml#id-41019"/>
    </sourceConnections>
    <sourceConnections
        xsi:type="archimate:DiagramModelArchimateConnection"
        id="9c196f2a-653f-4db6-992d-50260db1dcdb"
        source="id-38592"
        target="id-38502">
      <archimateRelationship
          xsi:type="archimate:AggregationRelationship"
          href="AggregationRelationship_id-28808.xml#id-28808"/>
    </sourceConnections>
    <sourceConnections
        xsi:type="archimate:DiagramModelArchimateConnection"
        id="840c8918-282d-42fd-8373-cac01015d660"
        source="id-38592"
        target="id-38505">
      <archimateRelationship
          xsi:type="archimate:AggregationRelationship"
          href="AggregationRelationship_id-41025.xml#id-41025"/>
    </sourceConnections>
    <sourceConnections
        xsi:type="archimate:DiagramModelArchimateConnection"
        id="285db926-e376-4545-a43a-f1e7f16fdc9f"
        source="id-38592"
        target="id-38509">
      <archimateRelationship
          xsi:type="archimate:AggregationRelationship"
          href="AggregationRelationship_id-26794.xml#id-26794"/>
    </sourceConnections>
    <sourceConnections
        xsi:type="archimate:DiagramModelArchimateConnection"
        id="b0838652-ea70-4865-85fd-f04113f3779b"
        source="id-38592"
        target="id-38512">
      <archimateRelationship
          xsi:type="archimate:AggregationRelationship"
          href="AggregationRelationship_id-40998.xml#id-40998"/>
    </sourceConnections>
    <sourceConnections
        xsi:type="archimate:DiagramModelArchimateConnection"
        id="51bc31ca-48f2-4ad5-98b2-4bbc17e16767"
        source="id-38592"
        target="id-38515">
      <archimateRelationship
          xsi:type="archimate:AggregationRelationship"
          href="AggregationRelationship_id-41002.xml#id-41002"/>
    </sourceConnections>
    <sourceConnections
        xsi:type="archimate:DiagramModelArchimateConnection"
        id="8ffb58ed-532d-4fc1-a289-12746f158f75"
        source="id-38592"
        target="id-38517">
      <archimateRelationship
          xsi:type="archimate:AggregationRelationship"
          href="AggregationRelationship_id-40962.xml#id-40962"/>
    </sourceConnections>
    <bounds
        x="47"
        y="973"
        width="1480"
        height="153"/>
    <children
        xsi:type="archimate:DiagramModelArchimateObject"
        id="id-38594"
        targetConnections="abcbd556-06fa-479a-abba-fec02413e493"
        font="1|Arial|10.0|0|WINDOWS|1|0|0|0|0|0|0|0|0|1|0|0|0|0|Arial"
        fontColor="#000000"
        lineColor="#000000"
        fillColor="#ffffcc">
      <bounds
          x="1006"
          y="27"
          width="193"
          height="53"/>
      <archimateElement
          xsi:type="archimate:BusinessFunction"
          href="BusinessFunction_id-26680.xml#id-26680"/>
    </children>
    <children
        xsi:type="archimate:DiagramModelArchimateObject"
        id="id-38596"
        targetConnections="884e6e60-adc7-42bc-b729-4abba1a6f188"
        font="1|Arial|10.0|0|WINDOWS|1|0|0|0|0|0|0|0|0|1|0|0|0|0|Arial"
        fontColor="#000000"
        lineColor="#000000"
        fillColor="#ffffcc">
      <bounds
          x="1006"
          y="87"
          width="193"
          height="53"/>
      <archimateElement
          xsi:type="archimate:BusinessFunction"
          href="BusinessFunction_id-26716.xml#id-26716"/>
    </children>
    <children
        xsi:type="archimate:DiagramModelArchimateObject"
        id="id-38599"
        targetConnections="f04b8064-2070-4cd0-89d7-0472854d3b22"
        font="1|Arial|10.0|0|WINDOWS|1|0|0|0|0|0|0|0|0|1|0|0|0|0|Arial"
        fontColor="#000000"
        lineColor="#000000"
        fillColor="#ffffcc">
      <bounds
          x="760"
          y="87"
          width="193"
          height="53"/>
      <archimateElement
          xsi:type="archimate:BusinessFunction"
          href="BusinessFunction_id-26738.xml#id-26738"/>
    </children>
    <children
        xsi:type="archimate:DiagramModelArchimateObject"
        id="id-38602"
        targetConnections="4a942697-4501-4042-b1a9-efe885f5bf84"
        font="1|Arial|10.0|0|WINDOWS|1|0|0|0|0|0|0|0|0|1|0|0|0|0|Arial"
        fontColor="#000000"
        lineColor="#000000"
        fillColor="#ffffcc">
      <bounds
          x="520"
          y="87"
          width="193"
          height="53"/>
      <archimateElement
          xsi:type="archimate:BusinessFunction"
          href="BusinessFunction_id-26758.xml#id-26758"/>
    </children>
    <children
        xsi:type="archimate:DiagramModelArchimateObject"
        id="id-38496"
        targetConnections="7357fa85-11de-4112-9d36-053353d55c30"
        font="1|Arial|10.0|0|WINDOWS|1|0|0|0|0|0|0|0|0|1|0|0|0|0|Arial"
        fontColor="#000000"
        lineColor="#000000"
        fillColor="#ffffcc">
      <bounds
          x="273"
          y="87"
          width="193"
          height="53"/>
      <archimateElement
          xsi:type="archimate:BusinessFunction"
          href="BusinessFunction_id-26776.xml#id-26776"/>
    </children>
    <children
        xsi:type="archimate:DiagramModelArchimateObject"
        id="id-38499"
        targetConnections="0b0adccc-1a7a-4da5-99b4-c17bdd447d0e"
        font="1|Arial|10.0|0|WINDOWS|1|0|0|0|0|0|0|0|0|1|0|0|0|0|Arial"
        fontColor="#000000"
        lineColor="#000000"
        fillColor="#ffffcc">
      <bounds
          x="33"
          y="87"
          width="193"
          height="53"/>
      <archimateElement
          xsi:type="archimate:BusinessFunction"
          href="BusinessFunction_id-26602.xml#id-26602"/>
    </children>
    <children
        xsi:type="archimate:DiagramModelArchimateObject"
        id="id-38502"
        targetConnections="9c196f2a-653f-4db6-992d-50260db1dcdb"
        font="1|Arial|10.0|0|WINDOWS|1|0|0|0|0|0|0|0|0|1|0|0|0|0|Arial"
        fontColor="#000000"
        lineColor="#000000"
        fillColor="#ffffcc">
      <bounds
          x="1246"
          y="87"
          width="193"
          height="53"/>
      <archimateElement
          xsi:type="archimate:BusinessFunction"
          href="BusinessFunction_id-26640.xml#id-26640"/>
    </children>
    <children
        xsi:type="archimate:DiagramModelArchimateObject"
        id="id-38505"
        targetConnections="840c8918-282d-42fd-8373-cac01015d660"
        font="1|Arial|10.0|0|WINDOWS|1|0|0|0|0|0|0|0|0|1|0|0|0|0|Arial"
        fontColor="#000000"
        lineColor="#000000"
        fillColor="#ffffcc">
      <bounds
          x="1246"
          y="27"
          width="193"
          height="53"/>
      <archimateElement
          xsi:type="archimate:BusinessFunction"
          href="BusinessFunction_id-26688.xml#id-26688"/>
    </children>
    <children
        xsi:type="archimate:DiagramModelArchimateObject"
        id="id-38509"
        targetConnections="285db926-e376-4545-a43a-f1e7f16fdc9f"
        font="1|Arial|10.0|0|WINDOWS|1|0|0|0|0|0|0|0|0|1|0|0|0|0|Arial"
        fontColor="#000000"
        lineColor="#000000"
        fillColor="#ffffcc">
      <bounds
          x="766"
          y="27"
          width="193"
          height="53"/>
      <archimateElement
          xsi:type="archimate:BusinessFunction"
          href="BusinessFunction_id-26626.xml#id-26626"/>
    </children>
    <children
        xsi:type="archimate:DiagramModelArchimateObject"
        id="id-38512"
        targetConnections="b0838652-ea70-4865-85fd-f04113f3779b"
        font="1|Arial|10.0|0|WINDOWS|1|0|0|0|0|0|0|0|0|1|0|0|0|0|Arial"
        fontColor="#000000"
        lineColor="#000000"
        fillColor="#ffffcc">
      <bounds
          x="520"
          y="27"
          width="193"
          height="53"/>
      <archimateElement
          xsi:type="archimate:BusinessFunction"
          href="BusinessFunction_id-26650.xml#id-26650"/>
    </children>
    <children
        xsi:type="archimate:DiagramModelArchimateObject"
        id="id-38515"
        targetConnections="51bc31ca-48f2-4ad5-98b2-4bbc17e16767"
        font="1|Arial|10.0|0|WINDOWS|1|0|0|0|0|0|0|0|0|1|0|0|0|0|Arial"
        fontColor="#000000"
        lineColor="#000000"
        fillColor="#ffffcc">
      <bounds
          x="280"
          y="27"
          width="193"
          height="53"/>
      <archimateElement
          xsi:type="archimate:BusinessFunction"
          href="BusinessFunction_id-26740.xml#id-26740"/>
    </children>
    <children
        xsi:type="archimate:DiagramModelArchimateObject"
        id="id-38517"
        targetConnections="8ffb58ed-532d-4fc1-a289-12746f158f75"
        font="1|Arial|10.0|0|WINDOWS|1|0|0|0|0|0|0|0|0|1|0|0|0|0|Arial"
        fontColor="#000000"
        lineColor="#000000"
        fillColor="#ffffcc">
      <bounds
          x="33"
          y="27"
          width="193"
          height="53"/>
      <archimateElement
          xsi:type="archimate:BusinessFunction"
          href="BusinessFunction_id-26584.xml#id-26584"/>
    </children>
    <archimateElement
        xsi:type="archimate:BusinessFunction"
        href="BusinessFunction_id-26674.xml#id-26674"/>
  </children>
  <children
      xsi:type="archimate:DiagramModelArchimateObject"
      id="id-38521"
      font="1|Arial|10.0|0|WINDOWS|1|0|0|0|0|0|0|0|0|1|0|0|0|0|Arial"
      fontColor="#000000"
      lineColor="#000000"
      textAlignment="1"
      fillColor="#ffe0e0">
    <sourceConnections
        xsi:type="archimate:DiagramModelArchimateConnection"
        id="id-38575"
        font="1|Arial|10.0|0|WINDOWS|1|0|0|0|0|0|0|0|0|1|0|0|0|0|Arial"
        fontColor="#000000"
        lineColor="#000000"
        source="id-38521"
        target="id-38503">
      <archimateRelationship
          xsi:type="archimate:AggregationRelationship"
          href="AggregationRelationship_id-38576.xml#id-38576"/>
    </sourceConnections>
    <sourceConnections
        xsi:type="archimate:DiagramModelArchimateConnection"
        id="id-38583"
        font="1|Arial|10.0|0|WINDOWS|1|0|0|0|0|0|0|0|0|1|0|0|0|0|Arial"
        fontColor="#000000"
        lineColor="#000000"
        source="id-38521"
        target="id-38520">
      <archimateRelationship
          xsi:type="archimate:AggregationRelationship"
          href="AggregationRelationship_id-38584.xml#id-38584"/>
    </sourceConnections>
    <bounds
        x="1667"
        y="93"
        width="304"
        height="89"/>
    <archimateElement
        xsi:type="archimate:Grouping"
        href="Grouping_id-35676.xml#id-35676"/>
  </children>
  <children
      xsi:type="archimate:DiagramModelArchimateObject"
      id="id-38524"
      font="1|Arial|10.0|0|WINDOWS|1|0|0|0|0|0|0|0|0|1|0|0|0|0|Arial"
      fontColor="#000000"
      lineColor="#000000"
      textAlignment="1"
      fillColor="#ffe0e0">
    <sourceConnections
        xsi:type="archimate:DiagramModelArchimateConnection"
        id="id-38580"
        font="1|Arial|10.0|0|WINDOWS|1|0|0|0|0|0|0|0|0|1|0|0|0|0|Arial"
        fontColor="#000000"
        lineColor="#000000"
        source="id-38524"
        target="id-38592">
      <archimateRelationship
          xsi:type="archimate:AggregationRelationship"
          href="AggregationRelationship_id-38581.xml#id-38581"/>
    </sourceConnections>
    <bounds
        x="1667"
        y="1024"
        width="304"
        height="89"/>
    <archimateElement
        xsi:type="archimate:Grouping"
        href="Grouping_id-35680.xml#id-35680"/>
  </children>
  <properties
      key="Architectuurlaag"
      value="Bedrijfsarchitectuur"/>
  <properties
      key="Domein"
      value="Niet domeingebonden"/>
  <properties
      key="Object ID"
      value="dcc17a74-48e0-4c86-a2ba-86e741e6578e"/>
  <properties
      key="Detailniveau"
      value="Samenhang"/>
  <properties
      key="Publiceren"
      value="Niet"/>
</archimate:ArchimateDiagramModel>
